{
"meta":{"test_sets":[],"test_metrics":[],"learn_metrics":[{"best_value":"Min","name":"RMSE"}],"launch_mode":"Train","parameters":"","iteration_count":1000,"learn_sets":["learn"],"name":"experiment"},
"iterations":[
{"learn":[0.6944948749],"iteration":0,"passed_time":0.006407102278,"remaining_time":6.400695176},
{"learn":[0.6688222921],"iteration":1,"passed_time":0.01396601757,"remaining_time":6.969042765},
{"learn":[0.6451768553],"iteration":2,"passed_time":0.02015677064,"remaining_time":6.698766775},
{"learn":[0.6231246042],"iteration":3,"passed_time":0.02616619627,"remaining_time":6.51538287},
{"learn":[0.6030909626],"iteration":4,"passed_time":0.03267723192,"remaining_time":6.502769153},
{"learn":[0.5840784368],"iteration":5,"passed_time":0.03887160123,"remaining_time":6.439728604},
{"learn":[0.5667673871],"iteration":6,"passed_time":0.04498848013,"remaining_time":6.381937252},
{"learn":[0.5511066314],"iteration":7,"passed_time":0.05089401317,"remaining_time":6.310857633},
{"learn":[0.535864804],"iteration":8,"passed_time":0.05690628943,"remaining_time":6.266014758},
{"learn":[0.5214344604],"iteration":9,"passed_time":0.06399245253,"remaining_time":6.335252801},
{"learn":[0.5089873297],"iteration":10,"passed_time":0.0698849147,"remaining_time":6.283289149},
{"learn":[0.497928072],"iteration":11,"passed_time":0.07586665259,"remaining_time":6.246354397},
{"learn":[0.4874452915],"iteration":12,"passed_time":0.08209860003,"remaining_time":6.233178325},
{"learn":[0.4779922211],"iteration":13,"passed_time":0.08797905379,"remaining_time":6.196239074},
{"learn":[0.4685274932],"iteration":14,"passed_time":0.0941895703,"remaining_time":6.185115116},
{"learn":[0.4604342953],"iteration":15,"passed_time":0.1003998403,"remaining_time":6.174590177},
{"learn":[0.4526490311],"iteration":16,"passed_time":0.1066694735,"remaining_time":6.168005438},
{"learn":[0.4452772657],"iteration":17,"passed_time":0.112948925,"remaining_time":6.161991355},
{"learn":[0.4384139982],"iteration":18,"passed_time":0.1189566571,"remaining_time":6.141920034},
{"learn":[0.4332700885],"iteration":19,"passed_time":0.1252699213,"remaining_time":6.138226143},
{"learn":[0.427653905],"iteration":20,"passed_time":0.1317589384,"remaining_time":6.142476221},
{"learn":[0.4221425296],"iteration":21,"passed_time":0.1378779856,"remaining_time":6.129303178},
{"learn":[0.4180888365],"iteration":22,"passed_time":0.143988244,"remaining_time":6.11637019},
{"learn":[0.4134719425],"iteration":23,"passed_time":0.1497524148,"remaining_time":6.089931536},
{"learn":[0.409512819],"iteration":24,"passed_time":0.1559231189,"remaining_time":6.081001636},
{"learn":[0.4053792137],"iteration":25,"passed_time":0.1625994303,"remaining_time":6.091224811},
{"learn":[0.4021335805],"iteration":26,"passed_time":0.1685244976,"remaining_time":6.073123561},
{"learn":[0.3989910887],"iteration":27,"passed_time":0.1750381695,"remaining_time":6.076325026},
{"learn":[0.3961005601],"iteration":28,"passed_time":0.1810817688,"remaining_time":6.063117155},
{"learn":[0.393193226],"iteration":29,"passed_time":0.1878692964,"remaining_time":6.074440583},
{"learn":[0.390668989],"iteration":30,"passed_time":0.1944073922,"remaining_time":6.076798807},
{"learn":[0.3880064183],"iteration":31,"passed_time":0.200837717,"remaining_time":6.07534094},
{"learn":[0.3856184364],"iteration":32,"passed_time":0.2077398123,"remaining_time":6.087406015},
{"learn":[0.3832979384],"iteration":33,"passed_time":0.2151015003,"remaining_time":6.111413215},
{"learn":[0.3812232833],"iteration":34,"passed_time":0.222845276,"remaining_time":6.144162609},
{"learn":[0.3792847228],"iteration":35,"passed_time":0.2298029472,"remaining_time":6.153612253},
{"learn":[0.3774935997],"iteration":36,"passed_time":0.2361459433,"remaining_time":6.146176849},
{"learn":[0.3758692156],"iteration":37,"passed_time":0.2426656836,"remaining_time":6.14327336},
{"learn":[0.3743539863],"iteration":38,"passed_time":0.2488939029,"remaining_time":6.133001043},
{"learn":[0.3731898405],"iteration":39,"passed_time":0.2550360225,"remaining_time":6.12086454},
{"learn":[0.3717057388],"iteration":40,"passed_time":0.2611756604,"remaining_time":6.108962399},
{"learn":[0.3701062881],"iteration":41,"passed_time":0.2672964394,"remaining_time":6.096904499},
{"learn":[0.3691616725],"iteration":42,"passed_time":0.2733950088,"remaining_time":6.084628452},
{"learn":[0.3679603265],"iteration":43,"passed_time":0.279599594,"remaining_time":6.074936634},
{"learn":[0.3667444478],"iteration":44,"passed_time":0.2864865273,"remaining_time":6.079880747},
{"learn":[0.3658039551],"iteration":45,"passed_time":0.2937450268,"remaining_time":6.092016425},
{"learn":[0.3648018068],"iteration":46,"passed_time":0.3026005261,"remaining_time":6.135708539},
{"learn":[0.3639603517],"iteration":47,"passed_time":0.3098667857,"remaining_time":6.14569125},
{"learn":[0.3630810261],"iteration":48,"passed_time":0.3167662552,"remaining_time":6.147851198},
{"learn":[0.3620452179],"iteration":49,"passed_time":0.32353683,"remaining_time":6.147199771},
{"learn":[0.3612617888],"iteration":50,"passed_time":0.3297670562,"remaining_time":6.136253653},
{"learn":[0.3604489293],"iteration":51,"passed_time":0.3360187445,"remaining_time":6.125880188},
{"learn":[0.359704161],"iteration":52,"passed_time":0.3426293681,"remaining_time":6.122075691},
{"learn":[0.35906411],"iteration":53,"passed_time":0.3487425587,"remaining_time":6.109452973},
{"learn":[0.358364396],"iteration":54,"passed_time":0.3548347637,"remaining_time":6.096706395},
{"learn":[0.3577073099],"iteration":55,"passed_time":0.3603578021,"remaining_time":6.074602949},
{"learn":[0.3569039322],"iteration":56,"passed_time":0.3665206599,"remaining_time":6.063666356},
{"learn":[0.3562943976],"iteration":57,"passed_time":0.3728249278,"remaining_time":6.055191068},
{"learn":[0.3557184323],"iteration":58,"passed_time":0.3787415534,"remaining_time":6.04060681},
{"learn":[0.3550217658],"iteration":59,"passed_time":0.3856481356,"remaining_time":6.041820791},
{"learn":[0.3545455098],"iteration":60,"passed_time":0.3917062658,"remaining_time":6.029707928},
{"learn":[0.3538810426],"iteration":61,"passed_time":0.39806741,"remaining_time":6.022374686},
{"learn":[0.3533412942],"iteration":62,"passed_time":0.4047468532,"remaining_time":6.019806372},
{"learn":[0.3527853109],"iteration":63,"passed_time":0.4111040157,"remaining_time":6.012396229},
{"learn":[0.3522213958],"iteration":64,"passed_time":0.4176094021,"remaining_time":6.007150631},
{"learn":[0.3516320992],"iteration":65,"passed_time":0.4237830801,"remaining_time":5.997172679},
{"learn":[0.3511445969],"iteration":66,"passed_time":0.4302697969,"remaining_time":5.99166747},
{"learn":[0.3507099559],"iteration":67,"passed_time":0.4368796836,"remaining_time":5.987821545},
{"learn":[0.3501874566],"iteration":68,"passed_time":0.4436038419,"remaining_time":5.985437346},
{"learn":[0.3497562457],"iteration":69,"passed_time":0.4504289025,"remaining_time":5.984269705},
{"learn":[0.3492804234],"iteration":70,"passed_time":0.4573753492,"remaining_time":5.984530978},
{"learn":[0.3489315853],"iteration":71,"passed_time":0.463375473,"remaining_time":5.972394985},
{"learn":[0.3481211931],"iteration":72,"passed_time":0.4698087743,"remaining_time":5.96592786},
{"learn":[0.3476705993],"iteration":73,"passed_time":0.4760854733,"remaining_time":5.957502004},
{"learn":[0.3472884035],"iteration":74,"passed_time":0.4822690642,"remaining_time":5.947985125},
{"learn":[0.3468830726],"iteration":75,"passed_time":0.4886263135,"remaining_time":5.940667285},
{"learn":[0.3465242698],"iteration":76,"passed_time":0.4948351052,"remaining_time":5.931594832},
{"learn":[0.3460893339],"iteration":77,"passed_time":0.5015803994,"remaining_time":5.928937541},
{"learn":[0.3456393256],"iteration":78,"passed_time":0.5081155647,"remaining_time":5.923727026},
{"learn":[0.3454360956],"iteration":79,"passed_time":0.5144066384,"remaining_time":5.915676341},
{"learn":[0.3450042972],"iteration":80,"passed_time":0.520458517,"remaining_time":5.904955273},
{"learn":[0.3446118572],"iteration":81,"passed_time":0.5270487575,"remaining_time":5.900375114},
{"learn":[0.3441524616],"iteration":82,"passed_time":0.5338762555,"remaining_time":5.898367787},
{"learn":[0.3438147659],"iteration":83,"passed_time":0.5403061715,"remaining_time":5.891910156},
{"learn":[0.3434720643],"iteration":84,"passed_time":0.5469103066,"remaining_time":5.887328594},
{"learn":[0.3431643858],"iteration":85,"passed_time":0.5533784665,"remaining_time":5.881254865},
{"learn":[0.3427558555],"iteration":86,"passed_time":0.5602992479,"remaining_time":5.879921993},
{"learn":[0.3423936761],"iteration":87,"passed_time":0.566779069,"remaining_time":5.87389217},
{"learn":[0.342038438],"iteration":88,"passed_time":0.5733892344,"remaining_time":5.869186433},
{"learn":[0.3417947851],"iteration":89,"passed_time":0.5821045468,"remaining_time":5.885723751},
{"learn":[0.3415693447],"iteration":90,"passed_time":0.5892765317,"remaining_time":5.886289751},
{"learn":[0.3413059578],"iteration":91,"passed_time":0.5968737925,"remaining_time":5.890884821},
{"learn":[0.3409765085],"iteration":92,"passed_time":0.6033135146,"remaining_time":5.883928578},
{"learn":[0.3406990609],"iteration":93,"passed_time":0.6102182236,"remaining_time":5.881465006},
{"learn":[0.3404401993],"iteration":94,"passed_time":0.6165866575,"remaining_time":5.873799211},
{"learn":[0.3401809515],"iteration":95,"passed_time":0.6234885748,"remaining_time":5.871184079},
{"learn":[0.339952573],"iteration":96,"passed_time":0.6311928288,"remaining_time":5.875949736},
{"learn":[0.3397108377],"iteration":97,"passed_time":0.6377548094,"remaining_time":5.869947328},
{"learn":[0.3394760062],"iteration":98,"passed_time":0.6452754634,"remaining_time":5.872658511},
{"learn":[0.3392232894],"iteration":99,"passed_time":0.6522012431,"remaining_time":5.869811188},
{"learn":[0.3390043593],"iteration":100,"passed_time":0.6585794806,"remaining_time":5.862009436},
{"learn":[0.3383718052],"iteration":101,"passed_time":0.6654260302,"remaining_time":5.85835858},
{"learn":[0.3378381132],"iteration":102,"passed_time":0.6721207483,"remaining_time":5.85332341},
{"learn":[0.3375801693],"iteration":103,"passed_time":0.6782734554,"remaining_time":5.843586693},
{"learn":[0.337403383],"iteration":104,"passed_time":0.6843723069,"remaining_time":5.833459187},
{"learn":[0.3372499949],"iteration":105,"passed_time":0.6909457023,"remaining_time":5.827409979},
{"learn":[0.3370165874],"iteration":106,"passed_time":0.6976300334,"remaining_time":5.822276821},
{"learn":[0.3367704615],"iteration":107,"passed_time":0.7040772667,"remaining_time":5.815156684},
{"learn":[0.3365707984],"iteration":108,"passed_time":0.7109222947,"remaining_time":5.811300593},
{"learn":[0.336531499],"iteration":109,"passed_time":0.7171665066,"remaining_time":5.802529008},
{"learn":[0.3362767692],"iteration":110,"passed_time":0.7243172117,"remaining_time":5.801063074},
{"learn":[0.3356371546],"iteration":111,"passed_time":0.7307788683,"remaining_time":5.794032455},
{"learn":[0.3354195087],"iteration":112,"passed_time":0.7376954068,"remaining_time":5.790582529},
{"learn":[0.3352961593],"iteration":113,"passed_time":0.7442958319,"remaining_time":5.784614974},
{"learn":[0.3350216022],"iteration":114,"passed_time":0.7512733785,"remaining_time":5.781538609},
{"learn":[0.3348123499],"iteration":115,"passed_time":0.757942046,"remaining_time":5.776041109},
{"learn":[0.3345578515],"iteration":116,"passed_time":0.7648392308,"remaining_time":5.772248212},
{"learn":[0.3343628858],"iteration":117,"passed_time":0.7718428984,"remaining_time":5.769198613},
{"learn":[0.334186127],"iteration":118,"passed_time":0.7787715087,"remaining_time":5.765526884},
{"learn":[0.3339863293],"iteration":119,"passed_time":0.7852836954,"remaining_time":5.758747099},
{"learn":[0.3337256384],"iteration":120,"passed_time":0.7922345543,"remaining_time":5.755158456},
{"learn":[0.3335864773],"iteration":121,"passed_time":0.7986385663,"remaining_time":5.747579191},
{"learn":[0.3335546236],"iteration":122,"passed_time":0.805787064,"remaining_time":5.745327277},
{"learn":[0.333271112],"iteration":123,"passed_time":0.8121932817,"remaining_time":5.737752539},
{"learn":[0.3330876673],"iteration":124,"passed_time":0.8188046432,"remaining_time":5.731632502},
{"learn":[0.3330522278],"iteration":125,"passed_time":0.8253790663,"remaining_time":5.725248444},
{"learn":[0.3328669269],"iteration":126,"passed_time":0.8318425883,"remaining_time":5.718099052},
{"learn":[0.3328227578],"iteration":127,"passed_time":0.8391856717,"remaining_time":5.716952389},
{"learn":[0.3326017824],"iteration":128,"passed_time":0.8457366778,"remaining_time":5.7103616},
{"learn":[0.3323515378],"iteration":129,"passed_time":0.8532379625,"remaining_time":5.71013098},
{"learn":[0.3321799603],"iteration":130,"passed_time":0.8597489539,"remaining_time":5.70322016},
{"learn":[0.3319046784],"iteration":131,"passed_time":0.8658939215,"remaining_time":5.693908514},
{"learn":[0.3317365863],"iteration":132,"passed_time":0.8725246098,"remaining_time":5.687810802},
{"learn":[0.3316953606],"iteration":133,"passed_time":0.8786899416,"remaining_time":5.678697682},
{"learn":[0.3314185991],"iteration":134,"passed_time":0.8847844122,"remaining_time":5.669174196},
{"learn":[0.3312565046],"iteration":135,"passed_time":0.8910873241,"remaining_time":5.661025353},
{"learn":[0.3311446012],"iteration":136,"passed_time":0.8980038114,"remaining_time":5.656768535},
{"learn":[0.3308824975],"iteration":137,"passed_time":0.9053100554,"remaining_time":5.654907737},
{"learn":[0.330685965],"iteration":138,"passed_time":0.9124537146,"remaining_time":5.651961498},
{"learn":[0.3304894597],"iteration":139,"passed_time":0.9192420529,"remaining_time":5.646772611},
{"learn":[0.3302515295],"iteration":140,"passed_time":0.9258158276,"remaining_time":5.640253872},
{"learn":[0.3300736551],"iteration":141,"passed_time":0.9322822393,"remaining_time":5.633085643},
{"learn":[0.3299054758],"iteration":142,"passed_time":0.9397245756,"remaining_time":5.631775953},
{"learn":[0.3296872531],"iteration":143,"passed_time":0.9463087476,"remaining_time":5.625279778},
{"learn":[0.3296220798],"iteration":144,"passed_time":0.9528381405,"remaining_time":5.61845938},
{"learn":[0.3294507366],"iteration":145,"passed_time":0.9601655958,"remaining_time":5.616311088},
{"learn":[0.3293990343],"iteration":146,"passed_time":0.9674948358,"remaining_time":5.614102687},
{"learn":[0.3291576948],"iteration":147,"passed_time":0.9735901258,"remaining_time":5.604721535},
{"learn":[0.3290726773],"iteration":148,"passed_time":0.9815265342,"remaining_time":5.60589987},
{"learn":[0.3289011722],"iteration":149,"passed_time":0.9885403717,"remaining_time":5.601728773},
{"learn":[0.328740832],"iteration":150,"passed_time":0.9957951082,"remaining_time":5.598874482},
{"learn":[0.3285898743],"iteration":151,"passed_time":1.002473483,"remaining_time":5.592746799},
{"learn":[0.3284182483],"iteration":152,"passed_time":1.008840694,"remaining_time":5.584889331},
{"learn":[0.328219068],"iteration":153,"passed_time":1.015832435,"remaining_time":5.580482075},
{"learn":[0.3279778261],"iteration":154,"passed_time":1.022585601,"remaining_time":5.574740857},
{"learn":[0.3278119235],"iteration":155,"passed_time":1.030944888,"remaining_time":5.577676191},
{"learn":[0.3276127475],"iteration":156,"passed_time":1.038630963,"remaining_time":5.576852879},
{"learn":[0.3274265941],"iteration":157,"passed_time":1.046279611,"remaining_time":5.575743242},
{"learn":[0.3271146509],"iteration":158,"passed_time":1.053271301,"remaining_time":5.571076505},
{"learn":[0.3270225222],"iteration":159,"passed_time":1.059759462,"remaining_time":5.563737178},
{"learn":[0.3269323985],"iteration":160,"passed_time":1.06603265,"remaining_time":5.555288159},
{"learn":[0.3268704255],"iteration":161,"passed_time":1.072870951,"remaining_time":5.54978924},
{"learn":[0.3265525053],"iteration":162,"passed_time":1.08018514,"remaining_time":5.54671756},
{"learn":[0.3263718737],"iteration":163,"passed_time":1.08670195,"remaining_time":5.539529452},
{"learn":[0.3261903768],"iteration":164,"passed_time":1.093882892,"remaining_time":5.535710393},
{"learn":[0.3261296198],"iteration":165,"passed_time":1.100485294,"remaining_time":5.528944186},
{"learn":[0.3260618274],"iteration":166,"passed_time":1.107737984,"remaining_time":5.525423598},
{"learn":[0.3258245299],"iteration":167,"passed_time":1.114770904,"remaining_time":5.52077019},
{"learn":[0.3257332215],"iteration":168,"passed_time":1.121357246,"remaining_time":5.51389273},
{"learn":[0.3255040864],"iteration":169,"passed_time":1.128701179,"remaining_time":5.510717522},
{"learn":[0.3254498138],"iteration":170,"passed_time":1.135341008,"remaining_time":5.504080091},
{"learn":[0.3252938741],"iteration":171,"passed_time":1.142407248,"remaining_time":5.499495356},
{"learn":[0.325108364],"iteration":172,"passed_time":1.149780701,"remaining_time":5.496350519},
{"learn":[0.3249166588],"iteration":173,"passed_time":1.156705985,"remaining_time":5.491029562},
{"learn":[0.3247647803],"iteration":174,"passed_time":1.163943257,"remaining_time":5.487161068},
{"learn":[0.3244396633],"iteration":175,"passed_time":1.170635808,"remaining_time":5.480704011},
{"learn":[0.3243114364],"iteration":176,"passed_time":1.178857027,"remaining_time":5.481352165},
{"learn":[0.3240524889],"iteration":177,"passed_time":1.186132194,"remaining_time":5.477531819},
{"learn":[0.3239982555],"iteration":178,"passed_time":1.193208963,"remaining_time":5.472762896},
{"learn":[0.323924756],"iteration":179,"passed_time":1.200038966,"remaining_time":5.466844178},
{"learn":[0.3237775133],"iteration":180,"passed_time":1.20650684,"remaining_time":5.459276807},
{"learn":[0.3236248292],"iteration":181,"passed_time":1.213004849,"remaining_time":5.45185696},
{"learn":[0.3234786262],"iteration":182,"passed_time":1.219558926,"remaining_time":5.444697498},
{"learn":[0.3234185357],"iteration":183,"passed_time":1.226790689,"remaining_time":5.440550011},
{"learn":[0.3232763635],"iteration":184,"passed_time":1.233737053,"remaining_time":5.435111882},
{"learn":[0.3230845214],"iteration":185,"passed_time":1.240557408,"remaining_time":5.429106075},
{"learn":[0.3227942858],"iteration":186,"passed_time":1.24730483,"remaining_time":5.422774473},
{"learn":[0.3226188447],"iteration":187,"passed_time":1.254485887,"remaining_time":5.418311385},
{"learn":[0.3225710784],"iteration":188,"passed_time":1.261538448,"remaining_time":5.413268154},
{"learn":[0.3224219495],"iteration":189,"passed_time":1.268660737,"remaining_time":5.408501036},
{"learn":[0.322370624],"iteration":190,"passed_time":1.275810857,"remaining_time":5.403827137},
{"learn":[0.3222375537],"iteration":191,"passed_time":1.28220213,"remaining_time":5.395933965},
{"learn":[0.3218675854],"iteration":192,"passed_time":1.289889197,"remaining_time":5.393474519},
{"learn":[0.3217051996],"iteration":193,"passed_time":1.297301012,"remaining_time":5.389817606},
{"learn":[0.3215535673],"iteration":194,"passed_time":1.30436323,"remaining_time":5.384678976},
{"learn":[0.3213032978],"iteration":195,"passed_time":1.31149651,"remaining_time":5.379812215},
{"learn":[0.3210825409],"iteration":196,"passed_time":1.318540192,"remaining_time":5.374557228},
{"learn":[0.3208536554],"iteration":197,"passed_time":1.325586317,"remaining_time":5.36929407},
{"learn":[0.3207142483],"iteration":198,"passed_time":1.332369415,"remaining_time":5.36295428},
{"learn":[0.3206079897],"iteration":199,"passed_time":1.33949363,"remaining_time":5.357974519},
{"learn":[0.3205594024],"iteration":200,"passed_time":1.346369125,"remaining_time":5.351984731},
{"learn":[0.3205106937],"iteration":201,"passed_time":1.353225708,"remaining_time":5.345911461},
{"learn":[0.3203812432],"iteration":202,"passed_time":1.36036377,"remaining_time":5.340935591},
{"learn":[0.3201615178],"iteration":203,"passed_time":1.367893181,"remaining_time":5.33746555},
{"learn":[0.3200275668],"iteration":204,"passed_time":1.375444564,"remaining_time":5.334041112},
{"learn":[0.3198752466],"iteration":205,"passed_time":1.382619002,"remaining_time":5.329123724},
{"learn":[0.319743427],"iteration":206,"passed_time":1.390366621,"remaining_time":5.32638034},
{"learn":[0.319453985],"iteration":207,"passed_time":1.397272555,"remaining_time":5.320383961},
{"learn":[0.3192990068],"iteration":208,"passed_time":1.404765244,"remaining_time":5.31659956},
{"learn":[0.3186828041],"iteration":209,"passed_time":1.411694593,"remaining_time":5.310660612},
{"learn":[0.3185090426],"iteration":210,"passed_time":1.42091627,"remaining_time":5.31328406},
{"learn":[0.3184124316],"iteration":211,"passed_time":1.428621245,"remaining_time":5.310158212},
{"learn":[0.3182951777],"iteration":212,"passed_time":1.436094631,"remaining_time":5.306133683},
{"learn":[0.3181489042],"iteration":213,"passed_time":1.442520023,"remaining_time":5.298227747},
{"learn":[0.3178260306],"iteration":214,"passed_time":1.449593316,"remaining_time":5.292701178},
{"learn":[0.3177295803],"iteration":215,"passed_time":1.456504878,"remaining_time":5.286573262},
{"learn":[0.3176820651],"iteration":216,"passed_time":1.463906712,"remaining_time":5.282207169},
{"learn":[0.3174759781],"iteration":217,"passed_time":1.470795534,"remaining_time":5.275972972},
{"learn":[0.3173376372],"iteration":218,"passed_time":1.477138325,"remaining_time":5.267785532},
{"learn":[0.317293825],"iteration":219,"passed_time":1.483848321,"remaining_time":5.260916775},
{"learn":[0.3171601141],"iteration":220,"passed_time":1.49044194,"remaining_time":5.253639236},
{"learn":[0.3168992613],"iteration":221,"passed_time":1.496090126,"remaining_time":5.243054584},
{"learn":[0.3168004207],"iteration":222,"passed_time":1.50150978,"remaining_time":5.231717933},
{"learn":[0.3167502517],"iteration":223,"passed_time":1.507785698,"remaining_time":5.223400453},
{"learn":[0.316638884],"iteration":224,"passed_time":1.514400337,"remaining_time":5.216267827},
{"learn":[0.3163492218],"iteration":225,"passed_time":1.521100533,"remaining_time":5.2094328},
{"learn":[0.3161714245],"iteration":226,"passed_time":1.52783269,"remaining_time":5.202707793},
{"learn":[0.3159738939],"iteration":227,"passed_time":1.53434106,"remaining_time":5.195224991},
{"learn":[0.3158630698],"iteration":228,"passed_time":1.540426505,"remaining_time":5.186326793},
{"learn":[0.3157167606],"iteration":229,"passed_time":1.547045807,"remaining_time":5.179240312},
{"learn":[0.3155607248],"iteration":230,"passed_time":1.553344274,"remaining_time":5.171089813},
{"learn":[0.3153206583],"iteration":231,"passed_time":1.55993466,"remaining_time":5.163921635},
{"learn":[0.3151515219],"iteration":232,"passed_time":1.566451591,"remaining_time":5.156516611},
{"learn":[0.3151073453],"iteration":233,"passed_time":1.573101781,"remaining_time":5.149555404},
{"learn":[0.3149172126],"iteration":234,"passed_time":1.580290622,"remaining_time":5.144350322},
{"learn":[0.3145963481],"iteration":235,"passed_time":1.586794006,"remaining_time":5.136909409},
{"learn":[0.3143731651],"iteration":236,"passed_time":1.59368062,"remaining_time":5.130710181},
{"learn":[0.3142700477],"iteration":237,"passed_time":1.600376307,"remaining_time":5.123893892},
{"learn":[0.3141351644],"iteration":238,"passed_time":1.606811485,"remaining_time":5.116249123},
{"learn":[0.3140137037],"iteration":239,"passed_time":1.61371328,"remaining_time":5.110092054},
{"learn":[0.3138356411],"iteration":240,"passed_time":1.620445641,"remaining_time":5.103395192},
{"learn":[0.3137439231],"iteration":241,"passed_time":1.626922185,"remaining_time":5.095896761},
{"learn":[0.3136595296],"iteration":242,"passed_time":1.633854547,"remaining_time":5.089826716},
{"learn":[0.3135021973],"iteration":243,"passed_time":1.640919077,"remaining_time":5.084159107},
{"learn":[0.3133917564],"iteration":244,"passed_time":1.647245761,"remaining_time":5.076206324},
{"learn":[0.313348785],"iteration":245,"passed_time":1.653204828,"remaining_time":5.067140002},
{"learn":[0.3131188366],"iteration":246,"passed_time":1.661057646,"remaining_time":5.063872094},
{"learn":[0.3130465204],"iteration":247,"passed_time":1.667992742,"remaining_time":5.057784443},
{"learn":[0.3129192868],"iteration":248,"passed_time":1.674552558,"remaining_time":5.050558116},
{"learn":[0.3128162403],"iteration":249,"passed_time":1.680577918,"remaining_time":5.041733754},
{"learn":[0.3125528755],"iteration":250,"passed_time":1.686600373,"remaining_time":5.032923024},
{"learn":[0.3125109139],"iteration":251,"passed_time":1.693115598,"remaining_time":5.025597094},
{"learn":[0.3124281834],"iteration":252,"passed_time":1.698933428,"remaining_time":5.01621846},
{"learn":[0.3123191681],"iteration":253,"passed_time":1.705062047,"remaining_time":5.007780657},
{"learn":[0.3121952683],"iteration":254,"passed_time":1.711483414,"remaining_time":5.00021625},
{"learn":[0.3120294192],"iteration":255,"passed_time":1.718012356,"remaining_time":4.992973409},
{"learn":[0.3119410232],"iteration":256,"passed_time":1.724086799,"remaining_time":4.984422147},
{"learn":[0.3119000509],"iteration":257,"passed_time":1.730211217,"remaining_time":4.97603381},
{"learn":[0.311832042],"iteration":258,"passed_time":1.736222476,"remaining_time":4.967339207},
{"learn":[0.3116472753],"iteration":259,"passed_time":1.742297678,"remaining_time":4.958847236},
{"learn":[0.3114867694],"iteration":260,"passed_time":1.748724317,"remaining_time":4.951368851},
{"learn":[0.3113431912],"iteration":261,"passed_time":1.754377382,"remaining_time":4.941719495},
{"learn":[0.3113055553],"iteration":262,"passed_time":1.761239791,"remaining_time":4.935489453},
{"learn":[0.3110773164],"iteration":263,"passed_time":1.771452696,"remaining_time":4.938595395},
{"learn":[0.3109541988],"iteration":264,"passed_time":1.77865404,"remaining_time":4.933247997},
{"learn":[0.3109158381],"iteration":265,"passed_time":1.787118255,"remaining_time":4.931371427},
{"learn":[0.3108773935],"iteration":266,"passed_time":1.795163482,"remaining_time":4.928295251},
{"learn":[0.3107560285],"iteration":267,"passed_time":1.802603153,"remaining_time":4.923528015},
{"learn":[0.3106328823],"iteration":268,"passed_time":1.809149368,"remaining_time":4.916312968},
{"learn":[0.3105120961],"iteration":269,"passed_time":1.816183068,"remaining_time":4.910420889},
{"learn":[0.3104293108],"iteration":270,"passed_time":1.822954334,"remaining_time":4.903814427},
{"learn":[0.3103135307],"iteration":271,"passed_time":1.829157947,"remaining_time":4.895687447},
{"learn":[0.3099975738],"iteration":272,"passed_time":1.835072413,"remaining_time":4.886804558},
{"learn":[0.3098618673],"iteration":273,"passed_time":1.842121621,"remaining_time":4.88094999},
{"learn":[0.3097643649],"iteration":274,"passed_time":1.848200554,"remaining_time":4.872528734},
{"learn":[0.3097284028],"iteration":275,"passed_time":1.854627701,"remaining_time":4.865037883},
{"learn":[0.3096519883],"iteration":276,"passed_time":1.860861381,"remaining_time":4.857049742},
{"learn":[0.3095711076],"iteration":277,"passed_time":1.867396645,"remaining_time":4.849857473},
{"learn":[0.3094926893],"iteration":278,"passed_time":1.873352453,"remaining_time":4.841172469},
{"learn":[0.3092518897],"iteration":279,"passed_time":1.879690678,"remaining_time":4.833490315},
{"learn":[0.3091565181],"iteration":280,"passed_time":1.885730855,"remaining_time":4.825055107},
{"learn":[0.3090270323],"iteration":281,"passed_time":1.89241032,"remaining_time":4.818264575},
{"learn":[0.3088416247],"iteration":282,"passed_time":1.89875547,"remaining_time":4.810627816},
{"learn":[0.3085222991],"iteration":283,"passed_time":1.905519305,"remaining_time":4.804055712},
{"learn":[0.3081165796],"iteration":284,"passed_time":1.912548271,"remaining_time":4.798147417},
{"learn":[0.3080809465],"iteration":285,"passed_time":1.918396183,"remaining_time":4.789282779},
{"learn":[0.3079453515],"iteration":286,"passed_time":1.924632681,"remaining_time":4.781404534},
{"learn":[0.3077044725],"iteration":287,"passed_time":1.931268129,"remaining_time":4.774523984},
{"learn":[0.3076698612],"iteration":288,"passed_time":1.937317163,"remaining_time":4.766202431},
{"learn":[0.3076341335],"iteration":289,"passed_time":1.943465275,"remaining_time":4.758139122},
{"learn":[0.3075995247],"iteration":290,"passed_time":1.949842823,"remaining_time":4.750647977},
{"learn":[0.307280932],"iteration":291,"passed_time":1.956195844,"remaining_time":4.743104991},
{"learn":[0.3072472443],"iteration":292,"passed_time":1.962986749,"remaining_time":4.736626728},
{"learn":[0.3071817829],"iteration":293,"passed_time":1.969431865,"remaining_time":4.729315975},
{"learn":[0.3070380447],"iteration":294,"passed_time":1.976012194,"remaining_time":4.722334227},
{"learn":[0.3070052365],"iteration":295,"passed_time":1.982008266,"remaining_time":4.713965605},
{"learn":[0.3068328106],"iteration":296,"passed_time":1.98897663,"remaining_time":4.707914379},
{"learn":[0.3067499481],"iteration":297,"passed_time":1.99544913,"remaining_time":4.700688889},
{"learn":[0.3066630221],"iteration":298,"passed_time":2.002185986,"remaining_time":4.694088214},
{"learn":[0.3065656602],"iteration":299,"passed_time":2.010225878,"remaining_time":4.690527048},
{"learn":[0.3063926238],"iteration":300,"passed_time":2.016755003,"remaining_time":4.683427732},
{"learn":[0.30623742],"iteration":301,"passed_time":2.023433255,"remaining_time":4.67667686},
{"learn":[0.3061300256],"iteration":302,"passed_time":2.030000825,"remaining_time":4.669671864},
{"learn":[0.3060718091],"iteration":303,"passed_time":2.036723942,"remaining_time":4.663025868},
{"learn":[0.3060137627],"iteration":304,"passed_time":2.042996072,"remaining_time":4.655351705},
{"learn":[0.3058482798],"iteration":305,"passed_time":2.049591028,"remaining_time":4.648418867},
{"learn":[0.3057769425],"iteration":306,"passed_time":2.055717115,"remaining_time":4.640429839},
{"learn":[0.305744343],"iteration":307,"passed_time":2.062861743,"remaining_time":4.634741318},
{"learn":[0.3054877353],"iteration":308,"passed_time":2.069755879,"remaining_time":4.628483211},
{"learn":[0.3053742876],"iteration":309,"passed_time":2.076274352,"remaining_time":4.621384847},
{"learn":[0.3052220784],"iteration":310,"passed_time":2.082818445,"remaining_time":4.614346973},
{"learn":[0.3051367045],"iteration":311,"passed_time":2.089982176,"remaining_time":4.608678644},
{"learn":[0.3050392765],"iteration":312,"passed_time":2.096798161,"remaining_time":4.602237497},
{"learn":[0.3049925543],"iteration":313,"passed_time":2.102874111,"remaining_time":4.594177198},
{"learn":[0.3048464041],"iteration":314,"passed_time":2.109645379,"remaining_time":4.587641539},
{"learn":[0.3047942404],"iteration":315,"passed_time":2.116342926,"remaining_time":4.580944814},
{"learn":[0.3047628922],"iteration":316,"passed_time":2.123049241,"remaining_time":4.574266976},
{"learn":[0.3046932308],"iteration":317,"passed_time":2.130332638,"remaining_time":4.568826601},
{"learn":[0.3046236487],"iteration":318,"passed_time":2.136770368,"remaining_time":4.561569343},
{"learn":[0.3044275883],"iteration":319,"passed_time":2.144295405,"remaining_time":4.556627735},
{"learn":[0.3043692437],"iteration":320,"passed_time":2.150820353,"remaining_time":4.549554579},
{"learn":[0.3042037001],"iteration":321,"passed_time":2.157495976,"remaining_time":4.542802087},
{"learn":[0.3041307803],"iteration":322,"passed_time":2.163695539,"remaining_time":4.53505226},
{"learn":[0.3040165747],"iteration":323,"passed_time":2.170000919,"remaining_time":4.527532781},
{"learn":[0.3038713792],"iteration":324,"passed_time":2.17664111,"remaining_time":4.520716152},
{"learn":[0.3037779435],"iteration":325,"passed_time":2.18263472,"remaining_time":4.512563808},
{"learn":[0.3036866638],"iteration":326,"passed_time":2.188626249,"remaining_time":4.504420384},
{"learn":[0.3035297574],"iteration":327,"passed_time":2.195161491,"remaining_time":4.497404029},
{"learn":[0.3034055194],"iteration":328,"passed_time":2.201302511,"remaining_time":4.489586581},
{"learn":[0.3033249122],"iteration":329,"passed_time":2.207637281,"remaining_time":4.482172661},
{"learn":[0.3032619642],"iteration":330,"passed_time":2.21363433,"remaining_time":4.474082679},
{"learn":[0.3031929705],"iteration":331,"passed_time":2.220016163,"remaining_time":4.466779509},
{"learn":[0.3030908212],"iteration":332,"passed_time":2.226561419,"remaining_time":4.459809209},
{"learn":[0.3029689417],"iteration":333,"passed_time":2.233163115,"remaining_time":4.452953996},
{"learn":[0.3028481498],"iteration":334,"passed_time":2.239945996,"remaining_time":4.446459963},
{"learn":[0.3025579505],"iteration":335,"passed_time":2.246655637,"remaining_time":4.439819472},
{"learn":[0.3025011935],"iteration":336,"passed_time":2.253241324,"remaining_time":4.432934712},
{"learn":[0.3024108925],"iteration":337,"passed_time":2.259864519,"remaining_time":4.426125182},
{"learn":[0.3022713797],"iteration":338,"passed_time":2.266422967,"remaining_time":4.419190506},
{"learn":[0.3021728933],"iteration":339,"passed_time":2.273272311,"remaining_time":4.412822722},
{"learn":[0.3021420371],"iteration":340,"passed_time":2.280291224,"remaining_time":4.406779815},
{"learn":[0.3019071918],"iteration":341,"passed_time":2.286774909,"remaining_time":4.399701433},
{"learn":[0.3018768054],"iteration":342,"passed_time":2.293270865,"remaining_time":4.392650024},
{"learn":[0.301740578],"iteration":343,"passed_time":2.299881732,"remaining_time":4.385820977},
{"learn":[0.3016746975],"iteration":344,"passed_time":2.305986532,"remaining_time":4.378032401},
{"learn":[0.3015933219],"iteration":345,"passed_time":2.311857171,"remaining_time":4.369810953},
{"learn":[0.3014451259],"iteration":346,"passed_time":2.318402077,"remaining_time":4.362871921},
{"learn":[0.3012125926],"iteration":347,"passed_time":2.324726473,"remaining_time":4.355522013},
{"learn":[0.3011490167],"iteration":348,"passed_time":2.331976446,"remaining_time":4.349904488},
{"learn":[0.3010349128],"iteration":349,"passed_time":2.339116275,"remaining_time":4.344073083},
{"learn":[0.3010026024],"iteration":350,"passed_time":2.346362437,"remaining_time":4.338430831},
{"learn":[0.3009028742],"iteration":351,"passed_time":2.353008241,"remaining_time":4.331674261},
{"learn":[0.3008725452],"iteration":352,"passed_time":2.359963586,"remaining_time":4.325485665},
{"learn":[0.3008440686],"iteration":353,"passed_time":2.366685388,"remaining_time":4.318866556},
{"learn":[0.3006994307],"iteration":354,"passed_time":2.372728001,"remaining_time":4.311012848},
{"learn":[0.3005723723],"iteration":355,"passed_time":2.379186017,"remaining_time":4.303920773},
{"learn":[0.3005239736],"iteration":356,"passed_time":2.387195166,"remaining_time":4.299626028},
{"learn":[0.3003430836],"iteration":357,"passed_time":2.395107759,"remaining_time":4.295137378},
{"learn":[0.3002679383],"iteration":358,"passed_time":2.40249005,"remaining_time":4.289682791},
{"learn":[0.3000277055],"iteration":359,"passed_time":2.409275649,"remaining_time":4.283156709},
{"learn":[0.2999673645],"iteration":360,"passed_time":2.415656319,"remaining_time":4.275912433},
{"learn":[0.2999092951],"iteration":361,"passed_time":2.421579518,"remaining_time":4.267866664},
{"learn":[0.2998810682],"iteration":362,"passed_time":2.427976916,"remaining_time":4.260664727},
{"learn":[0.2997522771],"iteration":363,"passed_time":2.435960686,"remaining_time":4.256239},
{"learn":[0.2997247209],"iteration":364,"passed_time":2.443062098,"remaining_time":4.250258719},
{"learn":[0.2995834701],"iteration":365,"passed_time":2.449859575,"remaining_time":4.24374582},
{"learn":[0.2994359169],"iteration":366,"passed_time":2.457026012,"remaining_time":4.237867754},
{"learn":[0.2993262865],"iteration":367,"passed_time":2.463975502,"remaining_time":4.231610101},
{"learn":[0.2992804015],"iteration":368,"passed_time":2.470384752,"remaining_time":4.224424874},
{"learn":[0.299165064],"iteration":369,"passed_time":2.477745024,"remaining_time":4.218863149},
{"learn":[0.2990674501],"iteration":370,"passed_time":2.485270946,"remaining_time":4.213572574},
{"learn":[0.2989835595],"iteration":371,"passed_time":2.49424112,"remaining_time":4.210708127},
{"learn":[0.2989261576],"iteration":372,"passed_time":2.5027612,"remaining_time":4.207054349},
{"learn":[0.2988988135],"iteration":373,"passed_time":2.509913771,"remaining_time":4.201085617},
{"learn":[0.29879382],"iteration":374,"passed_time":2.516385909,"remaining_time":4.193976515},
{"learn":[0.2987119481],"iteration":375,"passed_time":2.522868221,"remaining_time":4.186887685},
{"learn":[0.2985868967],"iteration":376,"passed_time":2.529920025,"remaining_time":4.180743172},
{"learn":[0.2985434125],"iteration":377,"passed_time":2.537329943,"remaining_time":4.175183134},
{"learn":[0.2984780109],"iteration":378,"passed_time":2.544500852,"remaining_time":4.169221712},
{"learn":[0.2984037969],"iteration":379,"passed_time":2.551871032,"remaining_time":4.163579053},
{"learn":[0.2983080833],"iteration":380,"passed_time":2.558409292,"remaining_time":4.156575727},
{"learn":[0.2982664822],"iteration":381,"passed_time":2.564665706,"remaining_time":4.149118865},
{"learn":[0.2980928359],"iteration":382,"passed_time":2.570950021,"remaining_time":4.141713218},
{"learn":[0.2980266365],"iteration":383,"passed_time":2.578393265,"remaining_time":4.136172529},
{"learn":[0.2979968511],"iteration":384,"passed_time":2.585459965,"remaining_time":4.130020463},
{"learn":[0.2978897398],"iteration":385,"passed_time":2.592103886,"remaining_time":4.123191156},
{"learn":[0.2978071955],"iteration":386,"passed_time":2.598687518,"remaining_time":4.116267308},
{"learn":[0.2977530873],"iteration":387,"passed_time":2.605389452,"remaining_time":4.109531815},
{"learn":[0.2977237991],"iteration":388,"passed_time":2.611921865,"remaining_time":4.102530231},
{"learn":[0.2976372899],"iteration":389,"passed_time":2.618559798,"remaining_time":4.095696095},
{"learn":[0.29760839],"iteration":390,"passed_time":2.625635159,"remaining_time":4.089544275},
{"learn":[0.2974452726],"iteration":391,"passed_time":2.632452797,"remaining_time":4.082988011},
{"learn":[0.2973754545],"iteration":392,"passed_time":2.639590027,"remaining_time":4.076924037},
{"learn":[0.29731598],"iteration":393,"passed_time":2.646811373,"remaining_time":4.07098399},
{"learn":[0.297263768],"iteration":394,"passed_time":2.653165412,"remaining_time":4.063709049},
{"learn":[0.2972032346],"iteration":395,"passed_time":2.659979704,"remaining_time":4.05714076},
{"learn":[0.2971759387],"iteration":396,"passed_time":2.666096859,"remaining_time":4.049512357},
{"learn":[0.2971189432],"iteration":397,"passed_time":2.672807753,"remaining_time":4.042789616},
{"learn":[0.2968922735],"iteration":398,"passed_time":2.679250484,"remaining_time":4.03566301},
{"learn":[0.2968087413],"iteration":399,"passed_time":2.68634877,"remaining_time":4.029523156},
{"learn":[0.2966918121],"iteration":400,"passed_time":2.693267286,"remaining_time":4.023109985},
{"learn":[0.2966295344],"iteration":401,"passed_time":2.700574481,"remaining_time":4.017272486},
{"learn":[0.2964649276],"iteration":402,"passed_time":2.709298685,"remaining_time":4.013526835},
{"learn":[0.2963919284],"iteration":403,"passed_time":2.716795093,"remaining_time":4.007945236},
{"learn":[0.296223396],"iteration":404,"passed_time":2.724460774,"remaining_time":4.002602865},
{"learn":[0.2961812178],"iteration":405,"passed_time":2.732039353,"remaining_time":3.997121616},
{"learn":[0.2961138594],"iteration":406,"passed_time":2.739924807,"remaining_time":3.992077176},
{"learn":[0.2959522387],"iteration":407,"passed_time":2.749956933,"remaining_time":3.990133589},
{"learn":[0.2958748172],"iteration":408,"passed_time":2.758169712,"remaining_time":3.985521515},
{"learn":[0.2956932418],"iteration":409,"passed_time":2.765824893,"remaining_time":3.980089481},
{"learn":[0.2955540519],"iteration":410,"passed_time":2.773296267,"remaining_time":3.974383215},
{"learn":[0.2955257584],"iteration":411,"passed_time":2.7802897,"remaining_time":3.967986271},
{"learn":[0.2954977898],"iteration":412,"passed_time":2.78739019,"remaining_time":3.961738599},
{"learn":[0.2954356998],"iteration":413,"passed_time":2.794684339,"remaining_time":3.955760924},
{"learn":[0.295382522],"iteration":414,"passed_time":2.802566125,"remaining_time":3.95060526},
{"learn":[0.2953284655],"iteration":415,"passed_time":2.810157597,"remaining_time":3.945028934},
{"learn":[0.2952406559],"iteration":416,"passed_time":2.817832426,"remaining_time":3.939559483},
{"learn":[0.2951966233],"iteration":417,"passed_time":2.826410764,"remaining_time":3.935337475},
{"learn":[0.2951481292],"iteration":418,"passed_time":2.833623016,"remaining_time":3.929200411},
{"learn":[0.2950144978],"iteration":419,"passed_time":2.840991144,"remaining_time":3.923273485},
{"learn":[0.2949570179],"iteration":420,"passed_time":2.849161573,"remaining_time":3.918443114},
{"learn":[0.2948139327],"iteration":421,"passed_time":2.856664028,"remaining_time":3.91268201},
{"learn":[0.2947500353],"iteration":422,"passed_time":2.864399749,"remaining_time":3.907230864},
{"learn":[0.2946507966],"iteration":423,"passed_time":2.871351995,"remaining_time":3.900704598},
{"learn":[0.2945497833],"iteration":424,"passed_time":2.879978731,"remaining_time":3.896441812},
{"learn":[0.2945086163],"iteration":425,"passed_time":2.888734002,"remaining_time":3.892331731},
{"learn":[0.29446752],"iteration":426,"passed_time":2.896130527,"remaining_time":3.886376562},
{"learn":[0.2944307447],"iteration":427,"passed_time":2.903271139,"remaining_time":3.880072643},
{"learn":[0.2943510962],"iteration":428,"passed_time":2.910474429,"remaining_time":3.87384825},
{"learn":[0.2941183385],"iteration":429,"passed_time":2.91737205,"remaining_time":3.867214113},
{"learn":[0.2940371532],"iteration":430,"passed_time":2.924354299,"remaining_time":3.860690478},
{"learn":[0.2939918307],"iteration":431,"passed_time":2.931086142,"remaining_time":3.853835483},
{"learn":[0.2939644427],"iteration":432,"passed_time":2.937676327,"remaining_time":3.84679556},
{"learn":[0.2938876636],"iteration":433,"passed_time":2.945344147,"remaining_time":3.841163104},
{"learn":[0.2938048919],"iteration":434,"passed_time":2.952060323,"remaining_time":3.834285248},
{"learn":[0.2937387111],"iteration":435,"passed_time":2.958108366,"remaining_time":3.82654385},
{"learn":[0.2934945187],"iteration":436,"passed_time":2.964169221,"remaining_time":3.818826708},
{"learn":[0.2934235264],"iteration":437,"passed_time":2.970206901,"remaining_time":3.811087394},
{"learn":[0.293396442],"iteration":438,"passed_time":2.976319849,"remaining_time":3.803452017},
{"learn":[0.293331013],"iteration":439,"passed_time":2.982329002,"remaining_time":3.795691457},
{"learn":[0.2932041922],"iteration":440,"passed_time":2.988769358,"remaining_time":3.788485422},
{"learn":[0.2931259145],"iteration":441,"passed_time":2.994910634,"remaining_time":3.78090528},
{"learn":[0.2930722018],"iteration":442,"passed_time":3.000390954,"remaining_time":3.772500591},
{"learn":[0.293045488],"iteration":443,"passed_time":3.005921407,"remaining_time":3.764171852},
{"learn":[0.2930202124],"iteration":444,"passed_time":3.011842727,"remaining_time":3.756343176},
{"learn":[0.2929224328],"iteration":445,"passed_time":3.017813625,"remaining_time":3.748584637},
{"learn":[0.2928963327],"iteration":446,"passed_time":3.023673747,"remaining_time":3.740697052},
{"learn":[0.2928588076],"iteration":447,"passed_time":3.029661135,"remaining_time":3.732975327},
{"learn":[0.2927871332],"iteration":448,"passed_time":3.035479998,"remaining_time":3.725054519},
{"learn":[0.2927032667],"iteration":449,"passed_time":3.041456153,"remaining_time":3.717335298},
{"learn":[0.2926425442],"iteration":450,"passed_time":3.047323961,"remaining_time":3.709491917},
{"learn":[0.2925448215],"iteration":451,"passed_time":3.053385839,"remaining_time":3.701892566},
{"learn":[0.2924255324],"iteration":452,"passed_time":3.059859846,"remaining_time":3.69479765},
{"learn":[0.2923724149],"iteration":453,"passed_time":3.065760802,"remaining_time":3.687016294},
{"learn":[0.2922718168],"iteration":454,"passed_time":3.072642396,"remaining_time":3.680417815},
{"learn":[0.2922184149],"iteration":455,"passed_time":3.079155328,"remaining_time":3.673378286},
{"learn":[0.2921268247],"iteration":456,"passed_time":3.085316675,"remaining_time":3.665923315},
{"learn":[0.2920653951],"iteration":457,"passed_time":3.092282328,"remaining_time":3.659425812},
{"learn":[0.2920394997],"iteration":458,"passed_time":3.09896847,"remaining_time":3.652596824},
{"learn":[0.2919690562],"iteration":459,"passed_time":3.10662761,"remaining_time":3.646910672},
{"learn":[0.291892875],"iteration":460,"passed_time":3.113917421,"remaining_time":3.640784143},
{"learn":[0.2918546146],"iteration":461,"passed_time":3.12055422,"remaining_time":3.633892144},
{"learn":[0.2918290403],"iteration":462,"passed_time":3.12722472,"remaining_time":3.627040334},
{"learn":[0.2917815674],"iteration":463,"passed_time":3.134052719,"remaining_time":3.620371244},
{"learn":[0.2917215856],"iteration":464,"passed_time":3.142218185,"remaining_time":3.615240278},
{"learn":[0.2916667634],"iteration":465,"passed_time":3.149671312,"remaining_time":3.609280002},
{"learn":[0.2915857706],"iteration":466,"passed_time":3.156338996,"remaining_time":3.602416884},
{"learn":[0.2914612684],"iteration":467,"passed_time":3.162802068,"remaining_time":3.595322009},
{"learn":[0.2912375696],"iteration":468,"passed_time":3.169443174,"remaining_time":3.588431398},
{"learn":[0.2911940052],"iteration":469,"passed_time":3.176009199,"remaining_time":3.581457182},
{"learn":[0.2910524991],"iteration":470,"passed_time":3.182588284,"remaining_time":3.574499368},
{"learn":[0.2909905717],"iteration":471,"passed_time":3.188910507,"remaining_time":3.567255821},
{"learn":[0.2909028399],"iteration":472,"passed_time":3.195331776,"remaining_time":3.560126524},
{"learn":[0.2908633574],"iteration":473,"passed_time":3.201493027,"remaining_time":3.552711672},
{"learn":[0.2907998818],"iteration":474,"passed_time":3.208407718,"remaining_time":3.546134846},
{"learn":[0.2907744584],"iteration":475,"passed_time":3.214744909,"remaining_time":3.538920866},
{"learn":[0.2907170779],"iteration":476,"passed_time":3.221088681,"remaining_time":3.531717778},
{"learn":[0.2906489782],"iteration":477,"passed_time":3.227639345,"remaining_time":3.524744222},
{"learn":[0.2906239504],"iteration":478,"passed_time":3.233991715,"remaining_time":3.51755675},
{"learn":[0.2905876828],"iteration":479,"passed_time":3.240372279,"remaining_time":3.510403302},
{"learn":[0.2905062438],"iteration":480,"passed_time":3.246960508,"remaining_time":3.503477138},
{"learn":[0.2904623812],"iteration":481,"passed_time":3.253880133,"remaining_time":3.496908525},
{"learn":[0.2903770395],"iteration":482,"passed_time":3.260094792,"remaining_time":3.489583866},
{"learn":[0.2902825261],"iteration":483,"passed_time":3.266554777,"remaining_time":3.48252534},
{"learn":[0.2902577529],"iteration":484,"passed_time":3.272838165,"remaining_time":3.475281762},
{"learn":[0.2902333234],"iteration":485,"passed_time":3.279646019,"remaining_time":3.468596818},
{"learn":[0.2900729983],"iteration":486,"passed_time":3.286174155,"remaining_time":3.461616718},
{"learn":[0.2900194657],"iteration":487,"passed_time":3.292478702,"remaining_time":3.454403884},
{"learn":[0.2899797689],"iteration":488,"passed_time":3.299056319,"remaining_time":3.447480121},
{"learn":[0.2899283993],"iteration":489,"passed_time":3.305609374,"remaining_time":3.440532206},
{"learn":[0.2898530813],"iteration":490,"passed_time":3.312042727,"remaining_time":3.433461809},
{"learn":[0.2897795235],"iteration":491,"passed_time":3.31847841,"remaining_time":3.426396407},
{"learn":[0.2897440435],"iteration":492,"passed_time":3.324694927,"remaining_time":3.419108171},
{"learn":[0.2895672438],"iteration":493,"passed_time":3.331665944,"remaining_time":3.4125971},
{"learn":[0.2895020801],"iteration":494,"passed_time":3.338774218,"remaining_time":3.406224203},
{"learn":[0.2894678269],"iteration":495,"passed_time":3.344914161,"remaining_time":3.398864389},
{"learn":[0.289350569],"iteration":496,"passed_time":3.351975775,"remaining_time":3.392442284},
{"learn":[0.2892830002],"iteration":497,"passed_time":3.358958535,"remaining_time":3.385938122},
{"learn":[0.2891805589],"iteration":498,"passed_time":3.366416455,"remaining_time":3.379909106},
{"learn":[0.2891248625],"iteration":499,"passed_time":3.37273707,"remaining_time":3.37273707},
{"learn":[0.2890764683],"iteration":500,"passed_time":3.379026529,"remaining_time":3.365537401},
{"learn":[0.2890201999],"iteration":501,"passed_time":3.385225823,"remaining_time":3.358251912},
{"learn":[0.2889959254],"iteration":502,"passed_time":3.391237499,"remaining_time":3.350785361},
{"learn":[0.2889519973],"iteration":503,"passed_time":3.397148472,"remaining_time":3.34322548},
{"learn":[0.28890797],"iteration":504,"passed_time":3.403107253,"remaining_time":3.33571899},
{"learn":[0.2888128178],"iteration":505,"passed_time":3.409824936,"remaining_time":3.328959523},
{"learn":[0.2887193709],"iteration":506,"passed_time":3.416414581,"remaining_time":3.322075717},
{"learn":[0.2886615668],"iteration":507,"passed_time":3.422538551,"remaining_time":3.314742061},
{"learn":[0.288637554],"iteration":508,"passed_time":3.42876057,"remaining_time":3.30750774},
{"learn":[0.2885232605],"iteration":509,"passed_time":3.435540371,"remaining_time":3.300813298},
{"learn":[0.2885002523],"iteration":510,"passed_time":3.441780255,"remaining_time":3.293601849},
{"learn":[0.2884767175],"iteration":511,"passed_time":3.448692128,"remaining_time":3.287034684},
{"learn":[0.2884402642],"iteration":512,"passed_time":3.455220691,"remaining_time":3.280102293},
{"learn":[0.2883698711],"iteration":513,"passed_time":3.461957094,"remaining_time":3.273367991},
{"learn":[0.2882624748],"iteration":514,"passed_time":3.468867517,"remaining_time":3.266797565},
{"learn":[0.2881949722],"iteration":515,"passed_time":3.475606004,"remaining_time":3.260064546},
{"learn":[0.2881348665],"iteration":516,"passed_time":3.482095163,"remaining_time":3.253098576},
{"learn":[0.2880370616],"iteration":517,"passed_time":3.488800649,"remaining_time":3.246335739},
{"learn":[0.2879069314],"iteration":518,"passed_time":3.496018858,"remaining_time":3.240048306},
{"learn":[0.2878568578],"iteration":519,"passed_time":3.502505645,"remaining_time":3.233082134},
{"learn":[0.287822357],"iteration":520,"passed_time":3.50932787,"remaining_time":3.226426199},
{"learn":[0.2877988144],"iteration":521,"passed_time":3.516498721,"remaining_time":3.220088867},
{"learn":[0.2877029272],"iteration":522,"passed_time":3.523779005,"remaining_time":3.213848156},
{"learn":[0.2875871408],"iteration":523,"passed_time":3.530953674,"remaining_time":3.207507536},
{"learn":[0.2875080206],"iteration":524,"passed_time":3.53819314,"remaining_time":3.201222365},
{"learn":[0.2874829488],"iteration":525,"passed_time":3.545210298,"remaining_time":3.194733235},
{"learn":[0.2874416096],"iteration":526,"passed_time":3.551515816,"remaining_time":3.18760338},
{"learn":[0.2873510554],"iteration":527,"passed_time":3.558299714,"remaining_time":3.18090429},
{"learn":[0.2873280679],"iteration":528,"passed_time":3.565267837,"remaining_time":3.174368906},
{"learn":[0.2872776439],"iteration":529,"passed_time":3.572521784,"remaining_time":3.168085356},
{"learn":[0.2872031172],"iteration":530,"passed_time":3.579350367,"remaining_time":3.161422452},
{"learn":[0.2871787376],"iteration":531,"passed_time":3.586017427,"remaining_time":3.154616835},
{"learn":[0.2871109619],"iteration":532,"passed_time":3.593993812,"remaining_time":3.148958931},
{"learn":[0.2870267763],"iteration":533,"passed_time":3.60058344,"remaining_time":3.142082178},
{"learn":[0.2869615219],"iteration":534,"passed_time":3.607081163,"remaining_time":3.135126619},
{"learn":[0.2869000202],"iteration":535,"passed_time":3.613890185,"remaining_time":3.12844225},
{"learn":[0.2868761373],"iteration":536,"passed_time":3.620634095,"remaining_time":3.121701277},
{"learn":[0.2868385594],"iteration":537,"passed_time":3.627026133,"remaining_time":3.114658129},
{"learn":[0.2868150741],"iteration":538,"passed_time":3.633855286,"remaining_time":3.107991256},
{"learn":[0.2867830815],"iteration":539,"passed_time":3.640644118,"remaining_time":3.101289434},
{"learn":[0.2867188315],"iteration":540,"passed_time":3.647159285,"remaining_time":3.094355105},
{"learn":[0.2866957056],"iteration":541,"passed_time":3.654010541,"remaining_time":3.087706324},
{"learn":[0.2866739885],"iteration":542,"passed_time":3.660395603,"remaining_time":3.080664439},
{"learn":[0.2866515554],"iteration":543,"passed_time":3.666361417,"remaining_time":3.073273541},
{"learn":[0.2866294012],"iteration":544,"passed_time":3.672389521,"remaining_time":3.065939875},
{"learn":[0.2866074988],"iteration":545,"passed_time":3.67831238,"remaining_time":3.058523481},
{"learn":[0.28658707],"iteration":546,"passed_time":3.684255109,"remaining_time":3.051129002},
{"learn":[0.2865657607],"iteration":547,"passed_time":3.690576106,"remaining_time":3.044051825},
{"learn":[0.2865166304],"iteration":548,"passed_time":3.696398674,"remaining_time":3.036567946},
{"learn":[0.2864798324],"iteration":549,"passed_time":3.70264782,"remaining_time":3.029439126},
{"learn":[0.286458906],"iteration":550,"passed_time":3.708469435,"remaining_time":3.021965111},
{"learn":[0.2864145807],"iteration":551,"passed_time":3.714553611,"remaining_time":3.014710177},
{"learn":[0.2863833824],"iteration":552,"passed_time":3.720612755,"remaining_time":3.007439243},
{"learn":[0.2863364378],"iteration":553,"passed_time":3.726887305,"remaining_time":3.000346098},
{"learn":[0.2862965204],"iteration":554,"passed_time":3.732843507,"remaining_time":2.99300065},
{"learn":[0.2862771173],"iteration":555,"passed_time":3.739368209,"remaining_time":2.986114182},
{"learn":[0.2862294001],"iteration":556,"passed_time":3.745476733,"remaining_time":2.978898012},
{"learn":[0.2862090606],"iteration":557,"passed_time":3.751594536,"remaining_time":2.971693163},
{"learn":[0.2861744696],"iteration":558,"passed_time":3.757516285,"remaining_time":2.964337534},
{"learn":[0.2861289029],"iteration":559,"passed_time":3.763487353,"remaining_time":2.957025777},
{"learn":[0.286052626],"iteration":560,"passed_time":3.769586813,"remaining_time":2.949819271},
{"learn":[0.2860220105],"iteration":561,"passed_time":3.775977842,"remaining_time":2.942843941},
{"learn":[0.2858769298],"iteration":562,"passed_time":3.782018471,"remaining_time":2.935598707},
{"learn":[0.2858047006],"iteration":563,"passed_time":3.788728286,"remaining_time":2.928875058},
{"learn":[0.2857626254],"iteration":564,"passed_time":3.79497269,"remaining_time":2.921793133},
{"learn":[0.2857240977],"iteration":565,"passed_time":3.801071943,"remaining_time":2.914602868},
{"learn":[0.285685489],"iteration":566,"passed_time":3.807253098,"remaining_time":2.907478997},
{"learn":[0.2856349686],"iteration":567,"passed_time":3.813302022,"remaining_time":2.900257876},
{"learn":[0.2855745521],"iteration":568,"passed_time":3.819819319,"remaining_time":2.893395653},
{"learn":[0.2854372642],"iteration":569,"passed_time":3.826098494,"remaining_time":2.886355004},
{"learn":[0.2854064272],"iteration":570,"passed_time":3.832185656,"remaining_time":2.879172761},
{"learn":[0.2853376852],"iteration":571,"passed_time":3.838555241,"remaining_time":2.87220567},
{"learn":[0.285317572],"iteration":572,"passed_time":3.844741466,"remaining_time":2.865104024},
{"learn":[0.2851942852],"iteration":573,"passed_time":3.851623176,"remaining_time":2.85852173},
{"learn":[0.2851200082],"iteration":574,"passed_time":3.857989379,"remaining_time":2.851557367},
{"learn":[0.2850553612],"iteration":575,"passed_time":3.864262316,"remaining_time":2.844526427},
{"learn":[0.2849804675],"iteration":576,"passed_time":3.870991193,"remaining_time":2.837832365},
{"learn":[0.2849416917],"iteration":577,"passed_time":3.87755404,"remaining_time":2.831016963},
{"learn":[0.2848317836],"iteration":578,"passed_time":3.884097973,"remaining_time":2.824188681},
{"learn":[0.2847842839],"iteration":579,"passed_time":3.890436734,"remaining_time":2.817212807},
{"learn":[0.2847644178],"iteration":580,"passed_time":3.896858559,"remaining_time":2.81029903},
{"learn":[0.2846991529],"iteration":581,"passed_time":3.903165439,"remaining_time":2.803304387},
{"learn":[0.2846450625],"iteration":582,"passed_time":3.909495114,"remaining_time":2.796328409},
{"learn":[0.2845637396],"iteration":583,"passed_time":3.916132519,"remaining_time":2.789573849},
{"learn":[0.2844586801],"iteration":584,"passed_time":3.923294969,"remaining_time":2.783192157},
{"learn":[0.284396948],"iteration":585,"passed_time":3.930216917,"remaining_time":2.77663789},
{"learn":[0.2842691115],"iteration":586,"passed_time":3.936649626,"remaining_time":2.769738153},
{"learn":[0.2842246515],"iteration":587,"passed_time":3.944377671,"remaining_time":2.76374762},
{"learn":[0.2841645457],"iteration":588,"passed_time":3.951033156,"remaining_time":2.757002762},
{"learn":[0.2841270581],"iteration":589,"passed_time":3.957287865,"remaining_time":2.749979703},
{"learn":[0.284012371],"iteration":590,"passed_time":3.963870437,"remaining_time":2.74318614},
{"learn":[0.2839752523],"iteration":591,"passed_time":3.970082052,"remaining_time":2.736137631},
{"learn":[0.2839394826],"iteration":592,"passed_time":3.976319765,"remaining_time":2.729109856},
{"learn":[0.2839198397],"iteration":593,"passed_time":3.982337734,"remaining_time":2.721934546},
{"learn":[0.2838758546],"iteration":594,"passed_time":3.98871775,"remaining_time":2.715009561},
{"learn":[0.2838411327],"iteration":595,"passed_time":3.99562981,"remaining_time":2.708447052},
{"learn":[0.2838227862],"iteration":596,"passed_time":4.001863139,"remaining_time":2.701425201},
{"learn":[0.2838033357],"iteration":597,"passed_time":4.008725645,"remaining_time":2.694828945},
{"learn":[0.2837554903],"iteration":598,"passed_time":4.015398974,"remaining_time":2.688105156},
{"learn":[0.2837249438],"iteration":599,"passed_time":4.021580502,"remaining_time":2.681053668},
{"learn":[0.2836615334],"iteration":600,"passed_time":4.02781483,"remaining_time":2.674040128},
{"learn":[0.2836275187],"iteration":601,"passed_time":4.034449515,"remaining_time":2.667293865},
{"learn":[0.2835912316],"iteration":602,"passed_time":4.041297199,"remaining_time":2.660688205},
{"learn":[0.2835621445],"iteration":603,"passed_time":4.047617866,"remaining_time":2.653736216},
{"learn":[0.2834919042],"iteration":604,"passed_time":4.054457093,"remaining_time":2.647124879},
{"learn":[0.2834713973],"iteration":605,"passed_time":4.060781168,"remaining_time":2.640177855},
{"learn":[0.2834169498],"iteration":606,"passed_time":4.066994929,"remaining_time":2.633161462},
{"learn":[0.2833893959],"iteration":607,"passed_time":4.073371882,"remaining_time":2.626252924},
{"learn":[0.28336123],"iteration":608,"passed_time":4.079719315,"remaining_time":2.619327179},
{"learn":[0.2832455008],"iteration":609,"passed_time":4.085986371,"remaining_time":2.612351942},
{"learn":[0.2832172551],"iteration":610,"passed_time":4.092530182,"remaining_time":2.605555223},
{"learn":[0.2831768806],"iteration":611,"passed_time":4.098520973,"remaining_time":2.598408722},
{"learn":[0.2831294442],"iteration":612,"passed_time":4.104890281,"remaining_time":2.591504957},
{"learn":[0.2830211959],"iteration":613,"passed_time":4.11170917,"remaining_time":2.584885569},
{"learn":[0.2829922458],"iteration":614,"passed_time":4.117991463,"remaining_time":2.577929615},
{"learn":[0.2829398822],"iteration":615,"passed_time":4.127119478,"remaining_time":2.572749805},
{"learn":[0.2829125326],"iteration":616,"passed_time":4.136232025,"remaining_time":2.567547594},
{"learn":[0.2828865848],"iteration":617,"passed_time":4.144099445,"remaining_time":2.561563087},
{"learn":[0.2828610214],"iteration":618,"passed_time":4.151912549,"remaining_time":2.555539065},
{"learn":[0.2828001196],"iteration":619,"passed_time":4.159739347,"remaining_time":2.549517664},
{"learn":[0.2827163024],"iteration":620,"passed_time":4.167157223,"remaining_time":2.543240882},
{"learn":[0.2826398941],"iteration":621,"passed_time":4.174095914,"remaining_time":2.536669221},
{"learn":[0.2825350626],"iteration":622,"passed_time":4.181589738,"remaining_time":2.530432314},
{"learn":[0.2824948019],"iteration":623,"passed_time":4.187768801,"remaining_time":2.523399149},
{"learn":[0.28237607],"iteration":624,"passed_time":4.19358037,"remaining_time":2.516148222},
{"learn":[0.2823540942],"iteration":625,"passed_time":4.19961519,"remaining_time":2.509035273},
{"learn":[0.2823277582],"iteration":626,"passed_time":4.205911522,"remaining_time":2.502081336},
{"learn":[0.2822802356],"iteration":627,"passed_time":4.212160853,"remaining_time":2.495101652},
{"learn":[0.2822227207],"iteration":628,"passed_time":4.218473805,"remaining_time":2.488161815},
{"learn":[0.2822024307],"iteration":629,"passed_time":4.224535255,"remaining_time":2.481076261},
{"learn":[0.2821155596],"iteration":630,"passed_time":4.230837637,"remaining_time":2.474134847},
{"learn":[0.2820498712],"iteration":631,"passed_time":4.237103094,"remaining_time":2.467173953},
{"learn":[0.281999519],"iteration":632,"passed_time":4.243385467,"remaining_time":2.460225065},
{"learn":[0.2819793219],"iteration":633,"passed_time":4.249353533,"remaining_time":2.453096835},
{"learn":[0.2818223288],"iteration":634,"passed_time":4.255998523,"remaining_time":2.446361355},
{"learn":[0.2817903961],"iteration":635,"passed_time":4.262353037,"remaining_time":2.439459915},
{"learn":[0.2817510594],"iteration":636,"passed_time":4.269715411,"remaining_time":2.433134528},
{"learn":[0.2817205192],"iteration":637,"passed_time":4.275960224,"remaining_time":2.426171788},
{"learn":[0.2816894479],"iteration":638,"passed_time":4.282031915,"remaining_time":2.419113492},
{"learn":[0.2816174528],"iteration":639,"passed_time":4.288433894,"remaining_time":2.412244065},
{"learn":[0.2815980134],"iteration":640,"passed_time":4.294833519,"remaining_time":2.405374779},
{"learn":[0.2815666729],"iteration":641,"passed_time":4.301356811,"remaining_time":2.398575916},
{"learn":[0.2815399113],"iteration":642,"passed_time":4.307586153,"remaining_time":2.391614707},
{"learn":[0.2815138275],"iteration":643,"passed_time":4.313628629,"remaining_time":2.384552472},
{"learn":[0.2814843948],"iteration":644,"passed_time":4.320497214,"remaining_time":2.377948079},
{"learn":[0.2814143128],"iteration":645,"passed_time":4.326640476,"remaining_time":2.3709454},
{"learn":[0.2813820992],"iteration":646,"passed_time":4.332951793,"remaining_time":2.364037068},
{"learn":[0.2813309831],"iteration":647,"passed_time":4.339263293,"remaining_time":2.357130678},
{"learn":[0.2812580558],"iteration":648,"passed_time":4.345501549,"remaining_time":2.350186508},
{"learn":[0.281209324],"iteration":649,"passed_time":4.352273541,"remaining_time":2.343531907},
{"learn":[0.2811316537],"iteration":650,"passed_time":4.358442135,"remaining_time":2.336553464},
{"learn":[0.2810704556],"iteration":651,"passed_time":4.365161043,"remaining_time":2.329871232},
{"learn":[0.2809680596],"iteration":652,"passed_time":4.372124871,"remaining_time":2.323319036},
{"learn":[0.28092639],"iteration":653,"passed_time":4.378008912,"remaining_time":2.316194317},
{"learn":[0.2808549549],"iteration":654,"passed_time":4.384385578,"remaining_time":2.309332862},
{"learn":[0.2807416729],"iteration":655,"passed_time":4.39058323,"remaining_time":2.302379011},
{"learn":[0.2806850358],"iteration":656,"passed_time":4.396480251,"remaining_time":2.295270512},
{"learn":[0.280649992],"iteration":657,"passed_time":4.403584831,"remaining_time":2.288793331},
{"learn":[0.2805928945],"iteration":658,"passed_time":4.410813525,"remaining_time":2.282378471},
{"learn":[0.2805728766],"iteration":659,"passed_time":4.416922907,"remaining_time":2.275384528},
{"learn":[0.2804626587],"iteration":660,"passed_time":4.423631359,"remaining_time":2.2687005},
{"learn":[0.2804068411],"iteration":661,"passed_time":4.430228557,"remaining_time":2.261959595},
{"learn":[0.2802649082],"iteration":662,"passed_time":4.436991259,"remaining_time":2.25530325},
{"learn":[0.2802455746],"iteration":663,"passed_time":4.443489743,"remaining_time":2.248512882},
{"learn":[0.2802269375],"iteration":664,"passed_time":4.449550388,"remaining_time":2.241502827},
{"learn":[0.2801322566],"iteration":665,"passed_time":4.455911033,"remaining_time":2.234646074},
{"learn":[0.2800788331],"iteration":666,"passed_time":4.462208677,"remaining_time":2.227759355},
{"learn":[0.2800602596],"iteration":667,"passed_time":4.4689192,"remaining_time":2.221079602},
{"learn":[0.2800270936],"iteration":668,"passed_time":4.475633152,"remaining_time":2.214401455},
{"learn":[0.2800074466],"iteration":669,"passed_time":4.481880093,"remaining_time":2.20749318},
{"learn":[0.2799882727],"iteration":670,"passed_time":4.487770579,"remaining_time":2.200412102},
{"learn":[0.2799689326],"iteration":671,"passed_time":4.494030509,"remaining_time":2.193514891},
{"learn":[0.2799192041],"iteration":672,"passed_time":4.500532978,"remaining_time":2.18673742},
{"learn":[0.2798688091],"iteration":673,"passed_time":4.507481705,"remaining_time":2.180176611},
{"learn":[0.2798402174],"iteration":674,"passed_time":4.513352902,"remaining_time":2.173095842},
{"learn":[0.2797757494],"iteration":675,"passed_time":4.519868698,"remaining_time":2.166327601},
{"learn":[0.2796540628],"iteration":676,"passed_time":4.526605448,"remaining_time":2.159665524},
{"learn":[0.2796278183],"iteration":677,"passed_time":4.533618821,"remaining_time":2.153134602},
{"learn":[0.2795668978],"iteration":678,"passed_time":4.540322923,"remaining_time":2.146456051},
{"learn":[0.2794890582],"iteration":679,"passed_time":4.547040215,"remaining_time":2.13978363},
{"learn":[0.2794223073],"iteration":680,"passed_time":4.553910153,"remaining_time":2.133182583},
{"learn":[0.27937909],"iteration":681,"passed_time":4.560620002,"remaining_time":2.126506101},
{"learn":[0.2793597782],"iteration":682,"passed_time":4.566952646,"remaining_time":2.119654449},
{"learn":[0.2791149015],"iteration":683,"passed_time":4.574102448,"remaining_time":2.113181833},
{"learn":[0.2790297501],"iteration":684,"passed_time":4.581143477,"remaining_time":2.106657219},
{"learn":[0.2790116672],"iteration":685,"passed_time":4.587329354,"remaining_time":2.099739675},
{"learn":[0.278967006],"iteration":686,"passed_time":4.59356139,"remaining_time":2.092845291},
{"learn":[0.2788983069],"iteration":687,"passed_time":4.599770299,"remaining_time":2.085942345},
{"learn":[0.2788178767],"iteration":688,"passed_time":4.60642946,"remaining_time":2.079244647},
{"learn":[0.2786936384],"iteration":689,"passed_time":4.613195634,"remaining_time":2.07259514},
{"learn":[0.2786682687],"iteration":690,"passed_time":4.619487216,"remaining_time":2.065733068},
{"learn":[0.2786372546],"iteration":691,"passed_time":4.626143243,"remaining_time":2.059034854},
{"learn":[0.2786193398],"iteration":692,"passed_time":4.632526341,"remaining_time":2.052215854},
{"learn":[0.2785673531],"iteration":693,"passed_time":4.639044785,"remaining_time":2.045457787},
{"learn":[0.2785338369],"iteration":694,"passed_time":4.645251143,"remaining_time":2.038563451},
{"learn":[0.2785148813],"iteration":695,"passed_time":4.651758347,"remaining_time":2.031802497},
{"learn":[0.2784778349],"iteration":696,"passed_time":4.657925379,"remaining_time":2.02489439},
{"learn":[0.2783989916],"iteration":697,"passed_time":4.664002842,"remaining_time":2.017949654},
{"learn":[0.2783801548],"iteration":698,"passed_time":4.67010002,"remaining_time":2.011015888},
{"learn":[0.2783543007],"iteration":699,"passed_time":4.676347967,"remaining_time":2.004149129},
{"learn":[0.2782785357],"iteration":700,"passed_time":4.68223857,"remaining_time":1.997131715},
{"learn":[0.278245512],"iteration":701,"passed_time":4.688172193,"remaining_time":1.990135774},
{"learn":[0.2782280669],"iteration":702,"passed_time":4.694381946,"remaining_time":1.983259513},
{"learn":[0.2781065417],"iteration":703,"passed_time":4.700968899,"remaining_time":1.976543742},
{"learn":[0.2780784296],"iteration":704,"passed_time":4.706986443,"remaining_time":1.969590072},
{"learn":[0.2779458585],"iteration":705,"passed_time":4.713853668,"remaining_time":1.962992887},
{"learn":[0.2779046812],"iteration":706,"passed_time":4.721254256,"remaining_time":1.956615979},
{"learn":[0.2778297615],"iteration":707,"passed_time":4.727477657,"remaining_time":1.949750672},
{"learn":[0.2777941945],"iteration":708,"passed_time":4.733734856,"remaining_time":1.942901048},
{"learn":[0.2777766941],"iteration":709,"passed_time":4.740262349,"remaining_time":1.936163495},
{"learn":[0.2777018802],"iteration":710,"passed_time":4.746808776,"remaining_time":1.929434228},
{"learn":[0.2776323025],"iteration":711,"passed_time":4.7533677,"remaining_time":1.92271053},
{"learn":[0.2775832891],"iteration":712,"passed_time":4.761538967,"remaining_time":1.916636302},
{"learn":[0.277564719],"iteration":713,"passed_time":4.769201652,"remaining_time":1.910352482},
{"learn":[0.2775467382],"iteration":714,"passed_time":4.775941313,"remaining_time":1.903696887},
{"learn":[0.2775077204],"iteration":715,"passed_time":4.782553303,"remaining_time":1.896990416},
{"learn":[0.2774332658],"iteration":716,"passed_time":4.789305781,"remaining_time":1.89033966},
{"learn":[0.2774150075],"iteration":717,"passed_time":4.795858647,"remaining_time":1.883610221},
{"learn":[0.2773968613],"iteration":718,"passed_time":4.802424205,"remaining_time":1.876886233},
{"learn":[0.277340313],"iteration":719,"passed_time":4.809161722,"remaining_time":1.870229559},
{"learn":[0.2773038616],"iteration":720,"passed_time":4.816095647,"remaining_time":1.863648662},
{"learn":[0.2772727752],"iteration":721,"passed_time":4.823063252,"remaining_time":1.857079756},
{"learn":[0.2772447006],"iteration":722,"passed_time":4.829159536,"remaining_time":1.850175922},
{"learn":[0.2771643216],"iteration":723,"passed_time":4.836049194,"remaining_time":1.843576765},
{"learn":[0.2770963666],"iteration":724,"passed_time":4.842402703,"remaining_time":1.836773439},
{"learn":[0.2770782928],"iteration":725,"passed_time":4.848895488,"remaining_time":1.830023917},
{"learn":[0.2770296932],"iteration":726,"passed_time":4.855322966,"remaining_time":1.823250577},
{"learn":[0.2768802988],"iteration":727,"passed_time":4.862430045,"remaining_time":1.816732105},
{"learn":[0.2768622166],"iteration":728,"passed_time":4.868339151,"remaining_time":1.80976668},
{"learn":[0.27683703],"iteration":729,"passed_time":4.874746207,"remaining_time":1.802988323},
{"learn":[0.2767187286],"iteration":730,"passed_time":4.881527882,"remaining_time":1.796348838},
{"learn":[0.2765885008],"iteration":731,"passed_time":4.888142708,"remaining_time":1.789647877},
{"learn":[0.2765233254],"iteration":732,"passed_time":4.894331177,"remaining_time":1.782791848},
{"learn":[0.2765058165],"iteration":733,"passed_time":4.900881226,"remaining_time":1.776068673},
{"learn":[0.2764798086],"iteration":734,"passed_time":4.907064896,"remaining_time":1.769213874},
{"learn":[0.2764472129],"iteration":735,"passed_time":4.913653977,"remaining_time":1.762506318},
{"learn":[0.2763448256],"iteration":736,"passed_time":4.921377006,"remaining_time":1.756203735},
{"learn":[0.2762961684],"iteration":737,"passed_time":4.928791367,"remaining_time":1.749787721},
{"learn":[0.2762435397],"iteration":738,"passed_time":4.936091208,"remaining_time":1.743328559},
{"learn":[0.2762218733],"iteration":739,"passed_time":4.942782383,"remaining_time":1.73665327},
{"learn":[0.2762040901],"iteration":740,"passed_time":4.949475119,"remaining_time":1.729978483},
{"learn":[0.2761598495],"iteration":741,"passed_time":4.956448904,"remaining_time":1.723401371},
{"learn":[0.2760610587],"iteration":742,"passed_time":4.963734189,"remaining_time":1.716930937},
{"learn":[0.2760012853],"iteration":743,"passed_time":4.970450275,"remaining_time":1.71026246},
{"learn":[0.2758706446],"iteration":744,"passed_time":4.976761284,"remaining_time":1.703455205},
{"learn":[0.2758528744],"iteration":745,"passed_time":4.983243769,"remaining_time":1.696707664},
{"learn":[0.2758352537],"iteration":746,"passed_time":4.989690075,"remaining_time":1.68994858},
{"learn":[0.2757683403],"iteration":747,"passed_time":4.996507237,"remaining_time":1.683315272},
{"learn":[0.2755870877],"iteration":748,"passed_time":5.003165267,"remaining_time":1.676628147},
{"learn":[0.2755017502],"iteration":749,"passed_time":5.008985248,"remaining_time":1.669661749},
{"learn":[0.2754842815],"iteration":750,"passed_time":5.015246171,"remaining_time":1.662844603},
{"learn":[0.2754472775],"iteration":751,"passed_time":5.021292233,"remaining_time":1.655958077},
{"learn":[0.2754182863],"iteration":752,"passed_time":5.027655572,"remaining_time":1.649177857},
{"learn":[0.2753940515],"iteration":753,"passed_time":5.034274181,"remaining_time":1.642482027},
{"learn":[0.2753469279],"iteration":754,"passed_time":5.04076031,"remaining_time":1.635743412},
{"learn":[0.2753013732],"iteration":755,"passed_time":5.047533799,"remaining_time":1.62909821},
{"learn":[0.2752606585],"iteration":756,"passed_time":5.053843576,"remaining_time":1.622303816},
{"learn":[0.2751987996],"iteration":757,"passed_time":5.060521694,"remaining_time":1.615628298},
{"learn":[0.2751597396],"iteration":758,"passed_time":5.067568405,"remaining_time":1.60906981},
{"learn":[0.2751437173],"iteration":759,"passed_time":5.074288782,"remaining_time":1.602406984},
{"learn":[0.2751264509],"iteration":760,"passed_time":5.080585055,"remaining_time":1.595610812},
{"learn":[0.2750913374],"iteration":761,"passed_time":5.086742455,"remaining_time":1.588772578},
{"learn":[0.2750741575],"iteration":762,"passed_time":5.092819039,"remaining_time":1.581911025},
{"learn":[0.2750504912],"iteration":763,"passed_time":5.099669832,"remaining_time":1.575290681},
{"learn":[0.2750041491],"iteration":764,"passed_time":5.10606482,"remaining_time":1.568529716},
{"learn":[0.2749440808],"iteration":765,"passed_time":5.11215126,"remaining_time":1.56167545},
{"learn":[0.2749002771],"iteration":766,"passed_time":5.11905677,"remaining_time":1.555072005},
{"learn":[0.2748698204],"iteration":767,"passed_time":5.125400593,"remaining_time":1.548298096},
{"learn":[0.2748260608],"iteration":768,"passed_time":5.131803042,"remaining_time":1.541542916},
{"learn":[0.2747491471],"iteration":769,"passed_time":5.138725997,"remaining_time":1.534944129},
{"learn":[0.2747320324],"iteration":770,"passed_time":5.145310268,"remaining_time":1.528243906},
{"learn":[0.2747053657],"iteration":771,"passed_time":5.151026827,"remaining_time":1.521287716},
{"learn":[0.2746813284],"iteration":772,"passed_time":5.15715957,"remaining_time":1.51445695},
{"learn":[0.2745810351],"iteration":773,"passed_time":5.163147451,"remaining_time":1.50758569},
{"learn":[0.2745305328],"iteration":774,"passed_time":5.169304217,"remaining_time":1.50076574},
{"learn":[0.2744785864],"iteration":775,"passed_time":5.175663922,"remaining_time":1.49400608},
{"learn":[0.2743781684],"iteration":776,"passed_time":5.181586246,"remaining_time":1.487121921},
{"learn":[0.2742962804],"iteration":777,"passed_time":5.187775336,"remaining_time":1.480316355},
{"learn":[0.274237414],"iteration":778,"passed_time":5.194071022,"remaining_time":1.473542614},
{"learn":[0.2742125523],"iteration":779,"passed_time":5.199923978,"remaining_time":1.466645225},
{"learn":[0.2740891987],"iteration":780,"passed_time":5.206313493,"remaining_time":1.459900967},
{"learn":[0.2740674704],"iteration":781,"passed_time":5.212227511,"remaining_time":1.453025061},
{"learn":[0.2740426602],"iteration":782,"passed_time":5.218386757,"remaining_time":1.446219574},
{"learn":[0.2740121001],"iteration":783,"passed_time":5.224744863,"remaining_time":1.439470523},
{"learn":[0.2739634509],"iteration":784,"passed_time":5.231021485,"remaining_time":1.432700152},
{"learn":[0.2739383145],"iteration":785,"passed_time":5.237070661,"remaining_time":1.425869111},
{"learn":[0.2738510996],"iteration":786,"passed_time":5.243121278,"remaining_time":1.419040448},
{"learn":[0.2738347911],"iteration":787,"passed_time":5.250036272,"remaining_time":1.412446307},
{"learn":[0.2738178956],"iteration":788,"passed_time":5.256459046,"remaining_time":1.40571972},
{"learn":[0.2737604033],"iteration":789,"passed_time":5.262586979,"remaining_time":1.398915526},
{"learn":[0.2737435438],"iteration":790,"passed_time":5.268725658,"remaining_time":1.392115882},
{"learn":[0.2737223295],"iteration":791,"passed_time":5.275374852,"remaining_time":1.385451981},
{"learn":[0.2736787752],"iteration":792,"passed_time":5.281505107,"remaining_time":1.378652657},
{"learn":[0.2736487764],"iteration":793,"passed_time":5.287899414,"remaining_time":1.371923526},
{"learn":[0.2735462185],"iteration":794,"passed_time":5.294359935,"remaining_time":1.36521231},
{"learn":[0.27352056],"iteration":795,"passed_time":5.300522645,"remaining_time":1.358425401},
{"learn":[0.2734879407],"iteration":796,"passed_time":5.306727464,"remaining_time":1.351650784},
{"learn":[0.2734638532],"iteration":797,"passed_time":5.312888499,"remaining_time":1.344866512},
{"learn":[0.2734472835],"iteration":798,"passed_time":5.319260898,"remaining_time":1.338136972},
{"learn":[0.2734307534],"iteration":799,"passed_time":5.325403864,"remaining_time":1.331350966},
{"learn":[0.2732977056],"iteration":800,"passed_time":5.332043893,"remaining_time":1.324690056},
{"learn":[0.2731571033],"iteration":801,"passed_time":5.338345413,"remaining_time":1.317945626},
{"learn":[0.2730988182],"iteration":802,"passed_time":5.344383746,"remaining_time":1.311137731},
{"learn":[0.2730417522],"iteration":803,"passed_time":5.351166835,"remaining_time":1.304513308},
{"learn":[0.2729688699],"iteration":804,"passed_time":5.357757102,"remaining_time":1.297841783},
{"learn":[0.2728743151],"iteration":805,"passed_time":5.363807121,"remaining_time":1.291040424},
{"learn":[0.2728577252],"iteration":806,"passed_time":5.369882509,"remaining_time":1.284246994},
{"learn":[0.2728412637],"iteration":807,"passed_time":5.375581271,"remaining_time":1.277365847},
{"learn":[0.2727965903],"iteration":808,"passed_time":5.381687509,"remaining_time":1.270583825},
{"learn":[0.2725696599],"iteration":809,"passed_time":5.387996769,"remaining_time":1.263851094},
{"learn":[0.2724258349],"iteration":810,"passed_time":5.39421945,"remaining_time":1.257099231},
{"learn":[0.2724041533],"iteration":811,"passed_time":5.400533889,"remaining_time":1.250369915},
{"learn":[0.2723583069],"iteration":812,"passed_time":5.406970676,"remaining_time":1.243669762},
{"learn":[0.27231633],"iteration":813,"passed_time":5.412996359,"remaining_time":1.236876318},
{"learn":[0.2722880426],"iteration":814,"passed_time":5.419551664,"remaining_time":1.230204979},
{"learn":[0.2722527798],"iteration":815,"passed_time":5.425804127,"remaining_time":1.223465636},
{"learn":[0.2722218707],"iteration":816,"passed_time":5.431959159,"remaining_time":1.216705662},
{"learn":[0.2722061076],"iteration":817,"passed_time":5.438351404,"remaining_time":1.209999946},
{"learn":[0.272161325],"iteration":818,"passed_time":5.444590229,"remaining_time":1.203261088},
{"learn":[0.2721175],"iteration":819,"passed_time":5.450937676,"remaining_time":1.196547295},
{"learn":[0.2720810614],"iteration":820,"passed_time":5.456912436,"remaining_time":1.189753138},
{"learn":[0.2720516394],"iteration":821,"passed_time":5.46317431,"remaining_time":1.183023147},
{"learn":[0.2720352908],"iteration":822,"passed_time":5.469457376,"remaining_time":1.176298852},
{"learn":[0.2720135866],"iteration":823,"passed_time":5.475421489,"remaining_time":1.169507503},
{"learn":[0.2719698021],"iteration":824,"passed_time":5.481690023,"remaining_time":1.162782732},
{"learn":[0.2719535988],"iteration":825,"passed_time":5.487887418,"remaining_time":1.156044081},
{"learn":[0.2718891848],"iteration":826,"passed_time":5.493818818,"remaining_time":1.149251095},
{"learn":[0.2718634473],"iteration":827,"passed_time":5.500030497,"remaining_time":1.142518413},
{"learn":[0.2718477089],"iteration":828,"passed_time":5.506219126,"remaining_time":1.135782232},
{"learn":[0.271781935],"iteration":829,"passed_time":5.512164228,"remaining_time":1.128997492},
{"learn":[0.2717513132],"iteration":830,"passed_time":5.518819756,"remaining_time":1.122359252},
{"learn":[0.2717041276],"iteration":831,"passed_time":5.525037129,"remaining_time":1.115632497},
{"learn":[0.271688034],"iteration":832,"passed_time":5.531609577,"remaining_time":1.108978151},
{"learn":[0.2716377698],"iteration":833,"passed_time":5.538503971,"remaining_time":1.102388081},
{"learn":[0.2715682922],"iteration":834,"passed_time":5.544882988,"remaining_time":1.095695441},
{"learn":[0.2715530093],"iteration":835,"passed_time":5.551521956,"remaining_time":1.089054546},
{"learn":[0.2714989987],"iteration":836,"passed_time":5.558269987,"remaining_time":1.082434896},
{"learn":[0.2714560661],"iteration":837,"passed_time":5.56473464,"remaining_time":1.075760157},
{"learn":[0.2714312637],"iteration":838,"passed_time":5.57113277,"remaining_time":1.069073154},
{"learn":[0.2714095501],"iteration":839,"passed_time":5.577893444,"remaining_time":1.062455894},
{"learn":[0.2713729777],"iteration":840,"passed_time":5.58430531,"remaining_time":1.055772347},
{"learn":[0.2713033904],"iteration":841,"passed_time":5.59097869,"remaining_time":1.049138519},
{"learn":[0.2712779231],"iteration":842,"passed_time":5.597299449,"remaining_time":1.042438925},
{"learn":[0.2712014202],"iteration":843,"passed_time":5.603976952,"remaining_time":1.035806166},
{"learn":[0.271185928],"iteration":844,"passed_time":5.61046009,"remaining_time":1.02913765},
{"learn":[0.271084578],"iteration":845,"passed_time":5.617494234,"remaining_time":1.022569872},
{"learn":[0.2710415753],"iteration":846,"passed_time":5.624206229,"remaining_time":1.015942802},
{"learn":[0.2710091141],"iteration":847,"passed_time":5.633915365,"remaining_time":1.009852754},
{"learn":[0.2708739956],"iteration":848,"passed_time":5.641839277,"remaining_time":1.003436668},
{"learn":[0.2707802945],"iteration":849,"passed_time":5.649309514,"remaining_time":0.9969369731},
{"learn":[0.2707163966],"iteration":850,"passed_time":5.657061095,"remaining_time":0.9904842576},
{"learn":[0.2706360055],"iteration":851,"passed_time":5.664205135,"remaining_time":0.9839229578},
{"learn":[0.2706208194],"iteration":852,"passed_time":5.670839042,"remaining_time":0.9772723788},
{"learn":[0.2705984356],"iteration":853,"passed_time":5.677030402,"remaining_time":0.9705461812},
{"learn":[0.2705442741],"iteration":854,"passed_time":5.683517362,"remaining_time":0.9638713655},
{"learn":[0.2704733677],"iteration":855,"passed_time":5.689842099,"remaining_time":0.9571696989},
{"learn":[0.2703878554],"iteration":856,"passed_time":5.696279854,"remaining_time":0.9504877703},
{"learn":[0.2703631075],"iteration":857,"passed_time":5.702104197,"remaining_time":0.9437048905},
{"learn":[0.270347725],"iteration":858,"passed_time":5.7080596,"remaining_time":0.9369457551},
{"learn":[0.2702430842],"iteration":859,"passed_time":5.7146294,"remaining_time":0.930288507},
{"learn":[0.2702273449],"iteration":860,"passed_time":5.721016458,"remaining_time":0.9236019602},
{"learn":[0.2701821053],"iteration":861,"passed_time":5.727276006,"remaining_time":0.9168956947},
{"learn":[0.2701196477],"iteration":862,"passed_time":5.733585131,"remaining_time":0.9101983349},
{"learn":[0.2700854659],"iteration":863,"passed_time":5.740254054,"remaining_time":0.9035585085},
{"learn":[0.2700192793],"iteration":864,"passed_time":5.74782162,"remaining_time":0.8970588656},
{"learn":[0.2699716436],"iteration":865,"passed_time":5.754257539,"remaining_time":0.8903816516},
{"learn":[0.2699559925],"iteration":866,"passed_time":5.760734709,"remaining_time":0.8837113222},
{"learn":[0.2699312071],"iteration":867,"passed_time":5.766827302,"remaining_time":0.8769829537},
{"learn":[0.2699163373],"iteration":868,"passed_time":5.773949578,"remaining_time":0.8704112713},
{"learn":[0.2699013785],"iteration":869,"passed_time":5.781059319,"remaining_time":0.86383645},
{"learn":[0.2698867031],"iteration":870,"passed_time":5.788135882,"remaining_time":0.8572554865},
{"learn":[0.2698683702],"iteration":871,"passed_time":5.795017936,"remaining_time":0.8506448346},
{"learn":[0.2698309106],"iteration":872,"passed_time":5.800873532,"remaining_time":0.8438842366},
{"learn":[0.269753144],"iteration":873,"passed_time":5.807275047,"remaining_time":0.8372044118},
{"learn":[0.2696911395],"iteration":874,"passed_time":5.8135926,"remaining_time":0.8305132286},
{"learn":[0.2696235451],"iteration":875,"passed_time":5.819532469,"remaining_time":0.8237694363},
{"learn":[0.2696016403],"iteration":876,"passed_time":5.825704791,"remaining_time":0.8170600791},
{"learn":[0.2695812484],"iteration":877,"passed_time":5.831736983,"remaining_time":0.8103324737},
{"learn":[0.2695221684],"iteration":878,"passed_time":5.83839763,"remaining_time":0.8036929616},
{"learn":[0.2695056505],"iteration":879,"passed_time":5.844830918,"remaining_time":0.7970223979},
{"learn":[0.2694780686],"iteration":880,"passed_time":5.851526251,"remaining_time":0.7903877683},
{"learn":[0.2693770813],"iteration":881,"passed_time":5.858679272,"remaining_time":0.7838142336},
{"learn":[0.2693572549],"iteration":882,"passed_time":5.864980834,"remaining_time":0.7771265658},
{"learn":[0.2693196892],"iteration":883,"passed_time":5.871775751,"remaining_time":0.7705045103},
{"learn":[0.2692801463],"iteration":884,"passed_time":5.8783417,"remaining_time":0.7638523112},
{"learn":[0.2692316197],"iteration":885,"passed_time":5.885006696,"remaining_time":0.7572130512},
{"learn":[0.2691791856],"iteration":886,"passed_time":5.891745319,"remaining_time":0.7505831127},
{"learn":[0.2691558018],"iteration":887,"passed_time":5.898446867,"remaining_time":0.7439482535},
{"learn":[0.2690675085],"iteration":888,"passed_time":5.905760217,"remaining_time":0.7373896334},
{"learn":[0.2690528379],"iteration":889,"passed_time":5.912243369,"remaining_time":0.7307267085},
{"learn":[0.2690076868],"iteration":890,"passed_time":5.918960544,"remaining_time":0.7240928162},
{"learn":[0.2689924136],"iteration":891,"passed_time":5.926194854,"remaining_time":0.71752135},
{"learn":[0.2689639677],"iteration":892,"passed_time":5.933494567,"remaining_time":0.710956236},
{"learn":[0.2687549162],"iteration":893,"passed_time":5.94034441,"remaining_time":0.7043361381},
{"learn":[0.2687131692],"iteration":894,"passed_time":5.946864829,"remaining_time":0.6976768793},
{"learn":[0.2686984507],"iteration":895,"passed_time":5.954258185,"remaining_time":0.6911192536},
{"learn":[0.2686540927],"iteration":896,"passed_time":5.961236563,"remaining_time":0.6845121137},
{"learn":[0.2686389577],"iteration":897,"passed_time":5.968029475,"remaining_time":0.6778830806},
{"learn":[0.268623904],"iteration":898,"passed_time":5.973905899,"remaining_time":0.6711507184},
{"learn":[0.2686025577],"iteration":899,"passed_time":5.980268179,"remaining_time":0.6644742421},
{"learn":[0.2685889215],"iteration":900,"passed_time":5.986394253,"remaining_time":0.6577725094},
{"learn":[0.2685678575],"iteration":901,"passed_time":5.992597674,"remaining_time":0.6510804568},
{"learn":[0.2684143467],"iteration":902,"passed_time":5.998949823,"remaining_time":0.6444054627},
{"learn":[0.2683180305],"iteration":903,"passed_time":6.004868628,"remaining_time":0.637685164},
{"learn":[0.2682843868],"iteration":904,"passed_time":6.010450632,"remaining_time":0.6309312818},
{"learn":[0.2682642953],"iteration":905,"passed_time":6.016787168,"remaining_time":0.6242582713},
{"learn":[0.2680906826],"iteration":906,"passed_time":6.023342166,"remaining_time":0.6176084029},
{"learn":[0.2680339196],"iteration":907,"passed_time":6.030008308,"remaining_time":0.6109700047},
{"learn":[0.2680116348],"iteration":908,"passed_time":6.03609608,"remaining_time":0.604273645},
{"learn":[0.2679559813],"iteration":909,"passed_time":6.042592957,"remaining_time":0.5976190836},
{"learn":[0.2678488456],"iteration":910,"passed_time":6.048899992,"remaining_time":0.5909463219},
{"learn":[0.2677880883],"iteration":911,"passed_time":6.054878196,"remaining_time":0.5842426329},
{"learn":[0.2677730463],"iteration":912,"passed_time":6.060749664,"remaining_time":0.5775303623},
{"learn":[0.2677092239],"iteration":913,"passed_time":6.067029967,"remaining_time":0.5708583995},
{"learn":[0.267685497],"iteration":914,"passed_time":6.073218063,"remaining_time":0.5641787271},
{"learn":[0.2676555012],"iteration":915,"passed_time":6.079473722,"remaining_time":0.5575063238},
{"learn":[0.2676406769],"iteration":916,"passed_time":6.085611043,"remaining_time":0.5508241184},
{"learn":[0.2676246973],"iteration":917,"passed_time":6.091616002,"remaining_time":0.5441312769},
{"learn":[0.2676088561],"iteration":918,"passed_time":6.097893436,"remaining_time":0.5374639482},
{"learn":[0.2675946626],"iteration":919,"passed_time":6.104151438,"remaining_time":0.5307957772},
{"learn":[0.2675642507],"iteration":920,"passed_time":6.110837926,"remaining_time":0.524165251},
{"learn":[0.2675477065],"iteration":921,"passed_time":6.117214569,"remaining_time":0.5175083909},
{"learn":[0.2675325439],"iteration":922,"passed_time":6.124720795,"remaining_time":0.5109463718},
{"learn":[0.2674918697],"iteration":923,"passed_time":6.130860069,"remaining_time":0.5042698758},
{"learn":[0.2674776684],"iteration":924,"passed_time":6.137456967,"remaining_time":0.497631646},
{"learn":[0.2674379075],"iteration":925,"passed_time":6.144184666,"remaining_time":0.4910039582},
{"learn":[0.2674228485],"iteration":926,"passed_time":6.150411701,"remaining_time":0.4843366281},
{"learn":[0.2674091857],"iteration":927,"passed_time":6.156673169,"remaining_time":0.4776729183},
{"learn":[0.2673947031],"iteration":928,"passed_time":6.163049702,"remaining_time":0.4710188685},
{"learn":[0.2673698202],"iteration":929,"passed_time":6.171398724,"remaining_time":0.4645138824},
{"learn":[0.2673438382],"iteration":930,"passed_time":6.177712938,"remaining_time":0.4578541275},
{"learn":[0.2673296362],"iteration":931,"passed_time":6.183900397,"remaining_time":0.4511858659},
{"learn":[0.2673172087],"iteration":932,"passed_time":6.19315828,"remaining_time":0.4447391262},
{"learn":[0.2673032808],"iteration":933,"passed_time":6.19944979,"remaining_time":0.4380767518},
{"learn":[0.267289519],"iteration":934,"passed_time":6.20607811,"remaining_time":0.4314385852},
{"learn":[0.2672686871],"iteration":935,"passed_time":6.212658835,"remaining_time":0.4247971853},
{"learn":[0.2672550557],"iteration":936,"passed_time":6.219258835,"remaining_time":0.4181572109},
{"learn":[0.2671997316],"iteration":937,"passed_time":6.226303994,"remaining_time":0.4115467459},
{"learn":[0.2671802943],"iteration":938,"passed_time":6.23297269,"remaining_time":0.4049108989},
{"learn":[0.2671513164],"iteration":939,"passed_time":6.239623056,"remaining_time":0.3982738121},
{"learn":[0.2671055883],"iteration":940,"passed_time":6.246583133,"remaining_time":0.3916561156},
{"learn":[0.2670854625],"iteration":941,"passed_time":6.252914618,"remaining_time":0.3849989892},
{"learn":[0.2670524735],"iteration":942,"passed_time":6.259879818,"remaining_time":0.3783808586},
{"learn":[0.2670318969],"iteration":943,"passed_time":6.266363875,"remaining_time":0.3717334502},
{"learn":[0.2670000004],"iteration":944,"passed_time":6.272293106,"remaining_time":0.3650540961},
{"learn":[0.2669873093],"iteration":945,"passed_time":6.278944848,"remaining_time":0.3584175706},
{"learn":[0.2669108396],"iteration":946,"passed_time":6.285914305,"remaining_time":0.3517987943},
{"learn":[0.2668965001],"iteration":947,"passed_time":6.292395656,"remaining_time":0.3451525044},
{"learn":[0.266844282],"iteration":948,"passed_time":6.29907479,"remaining_time":0.338517191},
{"learn":[0.2668300944],"iteration":949,"passed_time":6.305411348,"remaining_time":0.3318637551},
{"learn":[0.266815482],"iteration":950,"passed_time":6.313474455,"remaining_time":0.3252999456},
{"learn":[0.2667381692],"iteration":951,"passed_time":6.32078254,"remaining_time":0.318694918},
{"learn":[0.2667018191],"iteration":952,"passed_time":6.327679381,"remaining_time":0.3120681332},
{"learn":[0.2666673585],"iteration":953,"passed_time":6.334652391,"remaining_time":0.3054444549},
{"learn":[0.2666539621],"iteration":954,"passed_time":6.341378837,"remaining_time":0.2988084269},
{"learn":[0.2666132471],"iteration":955,"passed_time":6.347997713,"remaining_time":0.2921672587},
{"learn":[0.2665923446],"iteration":956,"passed_time":6.354369143,"remaining_time":0.285515019},
{"learn":[0.2665791486],"iteration":957,"passed_time":6.360814369,"remaining_time":0.2788666007},
{"learn":[0.2665658683],"iteration":958,"passed_time":6.366800605,"remaining_time":0.2721989831},
{"learn":[0.2664351281],"iteration":959,"passed_time":6.373815059,"remaining_time":0.2655756275},
{"learn":[0.2664147716],"iteration":960,"passed_time":6.380361013,"remaining_time":0.2589324448},
{"learn":[0.2664008757],"iteration":961,"passed_time":6.387521398,"remaining_time":0.2523137351},
{"learn":[0.2663872051],"iteration":962,"passed_time":6.394924692,"remaining_time":0.2457032332},
{"learn":[0.2663736706],"iteration":963,"passed_time":6.402046876,"remaining_time":0.2390805887},
{"learn":[0.2663611368],"iteration":964,"passed_time":6.40907604,"remaining_time":0.2324535351},
{"learn":[0.2663467224],"iteration":965,"passed_time":6.415338757,"remaining_time":0.2257986726},
{"learn":[0.2663244644],"iteration":966,"passed_time":6.421892393,"remaining_time":0.2191545491},
{"learn":[0.2662997491],"iteration":967,"passed_time":6.427910078,"remaining_time":0.2124928951},
{"learn":[0.2662866497],"iteration":968,"passed_time":6.435291112,"remaining_time":0.2058761862},
{"learn":[0.2662649141],"iteration":969,"passed_time":6.44179867,"remaining_time":0.1992308867},
{"learn":[0.2662268192],"iteration":970,"passed_time":6.447932696,"remaining_time":0.1925747149},
{"learn":[0.2662145186],"iteration":971,"passed_time":6.454782679,"remaining_time":0.1859402418},
{"learn":[0.2661290758],"iteration":972,"passed_time":6.461652861,"remaining_time":0.1793058862},
{"learn":[0.2660913661],"iteration":973,"passed_time":6.468599302,"remaining_time":0.172673082},
{"learn":[0.266052331],"iteration":974,"passed_time":6.475539861,"remaining_time":0.1660394836},
{"learn":[0.2659952724],"iteration":975,"passed_time":6.482496942,"remaining_time":0.1594056625},
{"learn":[0.2659349701],"iteration":976,"passed_time":6.489700419,"remaining_time":0.1527769802},
{"learn":[0.2658638372],"iteration":977,"passed_time":6.496339461,"remaining_time":0.1461344255},
{"learn":[0.2657845608],"iteration":978,"passed_time":6.50334758,"remaining_time":0.1394997949},
{"learn":[0.265728531],"iteration":979,"passed_time":6.510215292,"remaining_time":0.1328615366},
{"learn":[0.265618606],"iteration":980,"passed_time":6.517822072,"remaining_time":0.1262371247},
{"learn":[0.2656064001],"iteration":981,"passed_time":6.526100872,"remaining_time":0.1196230302},
{"learn":[0.2655818948],"iteration":982,"passed_time":6.53312836,"remaining_time":0.1129839086},
{"learn":[0.2655370849],"iteration":983,"passed_time":6.540191493,"remaining_time":0.1063445771},
{"learn":[0.2654489577],"iteration":984,"passed_time":6.548054968,"remaining_time":0.09971657311},
{"learn":[0.2653979718],"iteration":985,"passed_time":6.554371753,"remaining_time":0.09306410197},
{"learn":[0.2653426741],"iteration":986,"passed_time":6.56159134,"remaining_time":0.08642420205},
{"learn":[0.2653205125],"iteration":987,"passed_time":6.568742599,"remaining_time":0.07978229878},
{"learn":[0.2652731912],"iteration":988,"passed_time":6.575741257,"remaining_time":0.07313766817},
{"learn":[0.2651620332],"iteration":989,"passed_time":6.583813366,"remaining_time":0.06650316531},
{"learn":[0.2651215563],"iteration":990,"passed_time":6.590588399,"remaining_time":0.05985398142},
{"learn":[0.2650987244],"iteration":991,"passed_time":6.597784164,"remaining_time":0.05320793681},
{"learn":[0.264999562],"iteration":992,"passed_time":6.605609177,"remaining_time":0.04656522078},
{"learn":[0.2649485665],"iteration":993,"passed_time":6.613287843,"remaining_time":0.03991924251},
{"learn":[0.2649086502],"iteration":994,"passed_time":6.620442892,"remaining_time":0.03326855724},
{"learn":[0.2648740466],"iteration":995,"passed_time":6.627183952,"remaining_time":0.0266151966},
{"learn":[0.26485343],"iteration":996,"passed_time":6.634281745,"remaining_time":0.01996273344},
{"learn":[0.264839881],"iteration":997,"passed_time":6.641353624,"remaining_time":0.0133093259},
{"learn":[0.2648145549],"iteration":998,"passed_time":6.649089732,"remaining_time":0.006655745477},
{"learn":[0.2647955713],"iteration":999,"passed_time":6.655875024,"remaining_time":0}
]}